{"version": 0.6, "generator": "Overpass API 0.7.62.5 1bd436f1", "osm3s": {"timestamp_osm_base": "2025-04-16T13:57:29Z", "copyright": "The data included in this document is from www.openstreetmap.org. The data is made available under ODbL."}, "elements": [{"type": "node", "id": 20984570, "lat": 51.1726883, "lon": -4.2107948, "tags": {"source": "PGS"}}, {"type": "node", "id": 20984572, "lat": 51.1726671, "lon": -4.2100764, "tags": {"created_by": "dmgroom_coastlines", "source": "PGS"}}, {"type": "node", "id": 20984574, "lat": 51.1727593, "lon": -4.2098796, "tags": {"source": "PGS"}}, {"type": "node", "id": 48961710, "lat": 51.1734482, "lon": -4.2148642}, {"type": "node", "id": 48961713, "lat": 51.1452297, "lon": -4.2282612}, {"type": "node", "id": 48961716, "lat": 51.1602537, "lon": -4.2116421}, {"type": "node", "id": 48961723, "lat": 51.1445566, "lon": -4.2232144}, {"type": "node", "id": 48961725, "lat": 51.1463456, "lon": -4.2196127}, {"type": "node", "id": 48961727, "lat": 51.1479704, "lon": -4.2179787}, {"type": "node", "id": 48961730, "lat": 51.1493134, "lon": -4.2171536}, {"type": "node", "id": 48961732, "lat": 51.150407, "lon": -4.216464}, {"type": "node", "id": 48961735, "lat": 51.1545925, "lon": -4.2136294}, {"type": "node", "id": 48961738, "lat": 51.1676547, "lon": -4.2100097}, {"type": "node", "id": 48961745, "lat": 51.1695385, "lon": -4.209578}, {"type": "node", "id": 224705181, "lat": 51.1183735, "lon": -4.2307686}, {"type": "node", "id": 224705196, "lat": 51.0720707, "lon": -4.2087751}, {"type": "node", "id": 224705197, "lat": 51.0704622, "lon": -4.2045938}, {"type": "node", "id": 224705200, "lat": 51.0694607, "lon": -4.1992886}, {"type": "node", "id": 224705204, "lat": 51.0705122, "lon": -4.1982977}, {"type": "node", "id": 224705205, "lat": 51.07168, "lon": -4.205533}, {"type": "node", "id": 224705207, "lat": 51.0728977, "lon": -4.2070686}, {"type": "node", "id": 224705211, "lat": 51.0777304, "lon": -4.2161194}, {"type": "node", "id": 224705223, "lat": 51.1161306, "lon": -4.2210295}, {"type": "node", "id": 224705224, "lat": 51.1175762, "lon": -4.2214785}, {"type": "node", "id": 224705225, "lat": 51.1177933, "lon": -4.2265747}, {"type": "node", "id": 249630258, "lat": 51.17291, "lon": -4.2153792}, {"type": "node", "id": 249630259, "lat": 51.1692506, "lon": -4.2158942}, {"type": "node", "id": 249630260, "lat": 51.1648373, "lon": -4.2169241}, {"type": "node", "id": 249630261, "lat": 51.159347, "lon": -4.2176108}, {"type": "node", "id": 249630262, "lat": 51.1543945, "lon": -4.2194991}, {"type": "node", "id": 249630263, "lat": 51.1500875, "lon": -4.2227606}, {"type": "node", "id": 320372229, "lat": 51.1177917, "lon": -4.2255281}, {"type": "node", "id": 320372230, "lat": 51.1182138, "lon": -4.2293872}, {"type": "node", "id": 320372231, "lat": 51.1182311, "lon": -4.229848}, {"type": "node", "id": 320372232, "lat": 51.1183054, "lon": -4.2301541}, {"type": "node", "id": 320372492, "lat": 51.1137261, "lon": -4.2209184}, {"type": "node", "id": 320372494, "lat": 51.1145219, "lon": -4.22092}, {"type": "node", "id": 320372496, "lat": 51.1166933, "lon": -4.2210389}, {"type": "node", "id": 320372497, "lat": 51.1177397, "lon": -4.2217964}, {"type": "node", "id": 320372498, "lat": 51.1175682, "lon": -4.2227785}, {"type": "node", "id": 320372499, "lat": 51.1175103, "lon": -4.2237111}, {"type": "node", "id": 320372500, "lat": 51.117562, "lon": -4.2242763}, {"type": "node", "id": 320372501, "lat": 51.1176516, "lon": -4.2247355}, {"type": "node", "id": 320373106, "lat": 51.0862062, "lon": -4.2212186}, {"type": "node", "id": 320373108, "lat": 51.0870594, "lon": -4.2215654}, {"type": "node", "id": 320373112, "lat": 51.098096, "lon": -4.2219591}, {"type": "node", "id": 320373116, "lat": 51.1007925, "lon": -4.2218017, "tags": {"source": "PGS"}}, {"type": "node", "id": 320373117, "lat": 51.1055627, "lon": -4.2215555}, {"type": "node", "id": 320373118, "lat": 51.1062525, "lon": -4.2214777}, {"type": "node", "id": 320373119, "lat": 51.1069987, "lon": -4.2213999}, {"type": "node", "id": 320373120, "lat": 51.1083071, "lon": -4.2212838}, {"type": "node", "id": 320373121, "lat": 51.1091843, "lon": -4.2211963}, {"type": "node", "id": 320374029, "lat": 51.0745192, "lon": -4.2111678}, {"type": "node", "id": 320374030, "lat": 51.0748386, "lon": -4.2120141}, {"type": "node", "id": 320374031, "lat": 51.0755134, "lon": -4.2138058}, {"type": "node", "id": 320374035, "lat": 51.0766324, "lon": -4.2151224}, {"type": "node", "id": 320374036, "lat": 51.0781995, "lon": -4.2163246}, {"type": "node", "id": 320374037, "lat": 51.0792158, "lon": -4.2168251}, {"type": "node", "id": 320374038, "lat": 51.0804766, "lon": -4.2174541}, {"type": "node", "id": 320374039, "lat": 51.0822802, "lon": -4.218446}, {"type": "node", "id": 320374040, "lat": 51.0836317, "lon": -4.219513}, {"type": "node", "id": 320375123, "lat": 51.0665803, "lon": -4.1911784}, {"type": "node", "id": 320375124, "lat": 51.0692487, "lon": -4.1954981}, {"type": "node", "id": 320375125, "lat": 51.0699567, "lon": -4.1969244}, {"type": "node", "id": 320375127, "lat": 51.0708789, "lon": -4.1996968}, {"type": "node", "id": 320375129, "lat": 51.0708001, "lon": -4.2021601}, {"type": "node", "id": 320375131, "lat": 51.071683, "lon": -4.2047282}, {"type": "node", "id": 320375132, "lat": 51.0720325, "lon": -4.2057916}, {"type": "node", "id": 320375134, "lat": 51.0723494, "lon": -4.2062263}, {"type": "node", "id": 320375135, "lat": 51.0734387, "lon": -4.2084194}, {"type": "node", "id": 320377311, "lat": 51.1514928, "lon": -4.215394}, {"type": "node", "id": 320377313, "lat": 51.1537541, "lon": -4.2140269}, {"type": "node", "id": 320377315, "lat": 51.1552167, "lon": -4.2133258}, {"type": "node", "id": 320377316, "lat": 51.1559263, "lon": -4.2130245}, {"type": "node", "id": 320377317, "lat": 51.1567297, "lon": -4.21264}, {"type": "node", "id": 320377319, "lat": 51.1576395, "lon": -4.2123396}, {"type": "node", "id": 320377320, "lat": 51.1588249, "lon": -4.2120586}, {"type": "node", "id": 320377321, "lat": 51.1653823, "lon": -4.2104612}, {"type": "node", "id": 320377324, "lat": 51.1683542, "lon": -4.209884}, {"type": "node", "id": 320377493, "lat": 51.1455043, "lon": -4.2214033}, {"type": "node", "id": 320377494, "lat": 51.1460496, "lon": -4.2202616}, {"type": "node", "id": 320377496, "lat": 51.1466892, "lon": -4.2194078}, {"type": "node", "id": 320377497, "lat": 51.1471523, "lon": -4.2188866}, {"type": "node", "id": 320377498, "lat": 51.1475721, "lon": -4.2184664}, {"type": "node", "id": 320377500, "lat": 51.1487784, "lon": -4.2175479}, {"type": "node", "id": 320377501, "lat": 51.1497189, "lon": -4.2168098}, {"type": "node", "id": 320377502, "lat": 51.1501217, "lon": -4.2163672}, {"type": "node", "id": 320377685, "lat": 51.1447666, "lon": -4.2269223}, {"type": "node", "id": 320377686, "lat": 51.1447774, "lon": -4.2265017}, {"type": "node", "id": 320377687, "lat": 51.1444166, "lon": -4.2256863}, {"type": "node", "id": 320377688, "lat": 51.1444059, "lon": -4.2247679}, {"type": "node", "id": 320377689, "lat": 51.1444597, "lon": -4.2239182}, {"type": "node", "id": 320377690, "lat": 51.1446548, "lon": -4.2218882}, {"type": "node", "id": 320377691, "lat": 51.1452459, "lon": -4.2218325}, {"type": "node", "id": 325192187, "lat": 51.1704265, "lon": -4.2085205}, {"type": "node", "id": 325192426, "lat": 51.1704913, "lon": -4.2084164}, {"type": "node", "id": 325192427, "lat": 51.1705823, "lon": -4.2083397}, {"type": "node", "id": 325192428, "lat": 51.1706233, "lon": -4.2085237}, {"type": "node", "id": 325192430, "lat": 51.170755, "lon": -4.2088188}, {"type": "node", "id": 340456253, "lat": 51.1274478, "lon": -4.2384658}, {"type": "node", "id": 531626324, "lat": 51.130406, "lon": -4.2365286}, {"type": "node", "id": 531626338, "lat": 51.1298236, "lon": -4.2372475}, {"type": "node", "id": 531626347, "lat": 51.1294563, "lon": -4.2374051}, {"type": "node", "id": 531626363, "lat": 51.1282183, "lon": -4.2376635}, {"type": "node", "id": 531626364, "lat": 51.127381, "lon": -4.2377991}, {"type": "node", "id": 531626450, "lat": 51.1333179, "lon": -4.2373703}, {"type": "node", "id": 531626455, "lat": 51.1330063, "lon": -4.237838}, {"type": "node", "id": 531626463, "lat": 51.1323518, "lon": -4.2377029}, {"type": "node", "id": 531626466, "lat": 51.1319269, "lon": -4.2376058}, {"type": "node", "id": 531626470, "lat": 51.1315701, "lon": -4.2375543}, {"type": "node", "id": 531626474, "lat": 51.1311302, "lon": -4.2370748}, {"type": "node", "id": 531626479, "lat": 51.1309396, "lon": -4.2372024}, {"type": "node", "id": 542236254, "lat": 51.1274794, "lon": -4.2386011}, {"type": "node", "id": 567148280, "lat": 51.127344, "lon": -4.2412099}, {"type": "node", "id": 567148281, "lat": 51.1268163, "lon": -4.2440045}, {"type": "node", "id": 567148305, "lat": 51.1274383, "lon": -4.2401156}, {"type": "node", "id": 567148306, "lat": 51.1275056, "lon": -4.2393217}, {"type": "node", "id": 567148307, "lat": 51.127482, "lon": -4.2388046}, {"type": "node", "id": 567148338, "lat": 51.1332018, "lon": -4.2407075}, {"type": "node", "id": 567148339, "lat": 51.134136, "lon": -4.2443407}, {"type": "node", "id": 567148349, "lat": 51.1334072, "lon": -4.2424846}, {"type": "node", "id": 567148351, "lat": 51.1333016, "lon": -4.2422302}, {"type": "node", "id": 567148381, "lat": 51.1332299, "lon": -4.2394417}, {"type": "node", "id": 567148382, "lat": 51.1333243, "lon": -4.2392268}, {"type": "node", "id": 567148383, "lat": 51.1335231, "lon": -4.239276}, {"type": "node", "id": 567148386, "lat": 51.1334974, "lon": -4.2392587}, {"type": "node", "id": 567148387, "lat": 51.133434, "lon": -4.2392296}, {"type": "node", "id": 699784242, "lat": 51.1572498, "lon": -4.2184105}, {"type": "node", "id": 699784301, "lat": 51.1921022, "lon": -4.2076041}, {"type": "node", "id": 699784302, "lat": 51.191813, "lon": -4.2088225}, {"type": "node", "id": 699784308, "lat": 51.1927905, "lon": -4.2089924}, {"type": "node", "id": 699784315, "lat": 51.1927099, "lon": -4.206707}, {"type": "node", "id": 699784316, "lat": 51.1923645, "lon": -4.2069817}, {"type": "node", "id": 699784317, "lat": 51.1923974, "lon": -4.2072293}, {"type": "node", "id": 699784320, "lat": 51.1936162, "lon": -4.2062676}, {"type": "node", "id": 699784321, "lat": 51.1932177, "lon": -4.206499}, {"type": "node", "id": 699784322, "lat": 51.1929896, "lon": -4.2066469}, {"type": "node", "id": 699784327, "lat": 51.1934908, "lon": -4.2064627}, {"type": "node", "id": 699784335, "lat": 51.1938078, "lon": -4.2065249}, {"type": "node", "id": 699784338, "lat": 51.1936189, "lon": -4.2082733}, {"type": "node", "id": 825156635, "lat": 51.0677633, "lon": -4.2124186}, {"type": "node", "id": 825156638, "lat": 51.0683297, "lon": -4.2134057}, {"type": "node", "id": 825156639, "lat": 51.068478, "lon": -4.2141567}, {"type": "node", "id": 825156641, "lat": 51.0687612, "lon": -4.2150365}, {"type": "node", "id": 825156644, "lat": 51.0692196, "lon": -4.2161308}, {"type": "node", "id": 825156647, "lat": 51.0695567, "lon": -4.2166887}, {"type": "node", "id": 825156648, "lat": 51.069732, "lon": -4.2168604}, {"type": "node", "id": 825156651, "lat": 51.0698533, "lon": -4.2170535}, {"type": "node", "id": 825156654, "lat": 51.0698803, "lon": -4.2173539}, {"type": "node", "id": 825156656, "lat": 51.0699073, "lon": -4.217826}, {"type": "node", "id": 825156658, "lat": 51.0700556, "lon": -4.217547}, {"type": "node", "id": 825156667, "lat": 51.070123, "lon": -4.2169033}, {"type": "node", "id": 825156670, "lat": 51.0703387, "lon": -4.2157446}, {"type": "node", "id": 825156672, "lat": 51.0708106, "lon": -4.2161523}, {"type": "node", "id": 825156676, "lat": 51.0712556, "lon": -4.216517}, {"type": "node", "id": 825156679, "lat": 51.0718623, "lon": -4.2169677}, {"type": "node", "id": 825156680, "lat": 51.0722263, "lon": -4.2173968}, {"type": "node", "id": 825156681, "lat": 51.0725769, "lon": -4.217826}, {"type": "node", "id": 825156682, "lat": 51.072887, "lon": -4.2179976}, {"type": "node", "id": 825156683, "lat": 51.0730218, "lon": -4.2179547}, {"type": "node", "id": 825156684, "lat": 51.0730218, "lon": -4.2176328}, {"type": "node", "id": 825156685, "lat": 51.0729409, "lon": -4.2171393}, {"type": "node", "id": 825156688, "lat": 51.0724151, "lon": -4.2161308}, {"type": "node", "id": 825156691, "lat": 51.0716196, "lon": -4.2154656}, {"type": "node", "id": 825156696, "lat": 51.0713904, "lon": -4.2150365}, {"type": "node", "id": 825156700, "lat": 51.0710803, "lon": -4.2148004}, {"type": "node", "id": 825156703, "lat": 51.0704601, "lon": -4.2140065}, {"type": "node", "id": 825156704, "lat": 51.070123, "lon": -4.2135559}, {"type": "node", "id": 825156706, "lat": 51.0695837, "lon": -4.2131267}, {"type": "node", "id": 825156708, "lat": 51.0691387, "lon": -4.2126976}, {"type": "node", "id": 825156712, "lat": 51.0686802, "lon": -4.2124615}, {"type": "node", "id": 825156722, "lat": 51.0683432, "lon": -4.2123113}, {"type": "node", "id": 825156723, "lat": 51.0680061, "lon": -4.2122899}, {"type": "node", "id": 825156812, "lat": 51.0706354, "lon": -4.2158519}, {"type": "node", "id": 1298613934, "lat": 51.0958952, "lon": -4.22197}, {"type": "node", "id": 1561187275, "lat": 51.0656084, "lon": -4.1899808}, {"type": "node", "id": 1561249480, "lat": 51.0843431, "lon": -4.2201197}, {"type": "node", "id": 1561249485, "lat": 51.093743, "lon": -4.22203}, {"type": "node", "id": 1561249487, "lat": 51.1163464, "lon": -4.2206084}, {"type": "node", "id": 1561249503, "lat": 51.1132917, "lon": -4.2209292}, {"type": "node", "id": 1561249527, "lat": 51.1036834, "lon": -4.2217687}, {"type": "node", "id": 1561249536, "lat": 51.1118409, "lon": -4.2209748}, {"type": "node", "id": 1561249569, "lat": 51.1109797, "lon": -4.2210263}, {"type": "node", "id": 1561249582, "lat": 51.0896598, "lon": -4.2219924}, {"type": "node", "id": 1640545806, "lat": 51.0432637, "lon": -4.2393039}, {"type": "node", "id": 1640545830, "lat": 51.0430822, "lon": -4.2364404}, {"type": "node", "id": 1640545834, "lat": 51.0449541, "lon": -4.2387868}, {"type": "node", "id": 1640545835, "lat": 51.0452037, "lon": -4.2348408}, {"type": "node", "id": 1640545873, "lat": 51.047379, "lon": -4.2375425}, {"type": "node", "id": 1640545876, "lat": 51.0476818, "lon": -4.2333741}, {"type": "node", "id": 1640545879, "lat": 51.0497902, "lon": -4.2322401}, {"type": "node", "id": 1640545880, "lat": 51.0510723, "lon": -4.2362963}, {"type": "node", "id": 1640545911, "lat": 51.0542715, "lon": -4.2305022}, {"type": "node", "id": 1640546010, "lat": 51.0560559, "lon": -4.2295383}, {"type": "node", "id": 1640546072, "lat": 51.056985, "lon": -4.2291008}, {"type": "node", "id": 1640546164, "lat": 51.0572271, "lon": -4.2340175}, {"type": "node", "id": 1640546247, "lat": 51.0593084, "lon": -4.232807}, {"type": "node", "id": 1640546268, "lat": 51.0596217, "lon": -4.2275833}, {"type": "node", "id": 1640546276, "lat": 51.0599387, "lon": -4.2154545}, {"type": "node", "id": 1640546282, "lat": 51.0601523, "lon": -4.2159896}, {"type": "node", "id": 1640546293, "lat": 51.060275, "lon": -4.2168267}, {"type": "node", "id": 1640546296, "lat": 51.0603343, "lon": -4.2172641}, {"type": "node", "id": 1640546311, "lat": 51.0607319, "lon": -4.2179376}, {"type": "node", "id": 1640546321, "lat": 51.0614907, "lon": -4.2317165}, {"type": "node", "id": 1640546325, "lat": 51.060993, "lon": -4.2182712}, {"type": "node", "id": 1640546327, "lat": 51.0610302, "lon": -4.2265832}, {"type": "node", "id": 1640546338, "lat": 51.061169, "lon": -4.2183342}, {"type": "node", "id": 1640546383, "lat": 51.061812, "lon": -4.2258899}, {"type": "node", "id": 1640546413, "lat": 51.0623808, "lon": -4.2252204}, {"type": "node", "id": 1640546416, "lat": 51.0632708, "lon": -4.2300879}, {"type": "node", "id": 1640546427, "lat": 51.0629881, "lon": -4.2246299}, {"type": "node", "id": 1640546430, "lat": 51.0634363, "lon": -4.2241413}, {"type": "node", "id": 1640546432, "lat": 51.0637656, "lon": -4.2238109}, {"type": "node", "id": 1640546434, "lat": 51.0644737, "lon": -4.2262663}, {"type": "node", "id": 1640546438, "lat": 51.0648876, "lon": -4.2246376}, {"type": "node", "id": 1640546439, "lat": 51.064516, "lon": -4.2227382}, {"type": "node", "id": 1640546440, "lat": 51.0647939, "lon": -4.2219828}, {"type": "node", "id": 1640546442, "lat": 51.0651047, "lon": -4.223245}, {"type": "node", "id": 1640546443, "lat": 51.0650722, "lon": -4.2200002}, {"type": "node", "id": 1640546444, "lat": 51.0652535, "lon": -4.2217964}, {"type": "node", "id": 1640546445, "lat": 51.0652859, "lon": -4.2199293}, {"type": "node", "id": 1640686164, "lat": 51.0619514, "lon": -4.2083729}, {"type": "node", "id": 1640686166, "lat": 51.062224, "lon": -4.2093452}, {"type": "node", "id": 1640686167, "lat": 51.0622026, "lon": -4.2086607}, {"type": "node", "id": 1640686171, "lat": 51.0626043, "lon": -4.211113}, {"type": "node", "id": 1640686173, "lat": 51.0630984, "lon": -4.2114082}, {"type": "node", "id": 1640686178, "lat": 51.0634108, "lon": -4.2118388}, {"type": "node", "id": 1640686180, "lat": 51.063606, "lon": -4.2134924}, {"type": "node", "id": 1640686184, "lat": 51.0636481, "lon": -4.2123643}, {"type": "node", "id": 1640686189, "lat": 51.0640358, "lon": -4.2150525}, {"type": "node", "id": 1640686191, "lat": 51.0642973, "lon": -4.2156691}, {"type": "node", "id": 1640686192, "lat": 51.0648894, "lon": -4.2210337}, {"type": "node", "id": 1640686193, "lat": 51.0648314, "lon": -4.2167525}, {"type": "node", "id": 1640686194, "lat": 51.0651497, "lon": -4.2156902}, {"type": "node", "id": 1640686195, "lat": 51.0651557, "lon": -4.2189442}, {"type": "node", "id": 1640686196, "lat": 51.0651501, "lon": -4.2179963}, {"type": "node", "id": 1640686197, "lat": 51.0653639, "lon": -4.2184385}, {"type": "node", "id": 1640686198, "lat": 51.0654584, "lon": -4.2169025}, {"type": "node", "id": 1692199606, "lat": 51.0524475, "lon": -4.2311994}, {"type": "node", "id": 1692199626, "lat": 51.0584629, "lon": -4.2282851}, {"type": "node", "id": 1692199627, "lat": 51.0590152, "lon": -4.2279466}, {"type": "node", "id": 1692199636, "lat": 51.0639823, "lon": -4.2233965}, {"type": "node", "id": 1692199638, "lat": 51.0649573, "lon": -4.217237}, {"type": "node", "id": 1692199640, "lat": 51.0651679, "lon": -4.2182389}, {"type": "node", "id": 1746812736, "lat": 51.1331121, "lon": -4.2376631}, {"type": "node", "id": 1764178361, "lat": 51.1943337, "lon": -4.2069217}, {"type": "node", "id": 1764178436, "lat": 51.1940769, "lon": -4.2076202}, {"type": "node", "id": 1764178520, "lat": 51.194215, "lon": -4.2074384}, {"type": "node", "id": 1765376718, "lat": 51.0626964, "lon": -4.2089635}, {"type": "node", "id": 1765376719, "lat": 51.0652799, "lon": -4.2350545}, {"type": "node", "id": 1765376720, "lat": 51.0660521, "lon": -4.2128069}, {"type": "node", "id": 1765376729, "lat": 51.0689691, "lon": -4.2176373}, {"type": "node", "id": 1765376731, "lat": 51.0691648, "lon": -4.2355149}, {"type": "node", "id": 1765376734, "lat": 51.0701678, "lon": -4.2202386}, {"type": "node", "id": 1765376736, "lat": 51.0743506, "lon": -4.2346196}, {"type": "node", "id": 1765376738, "lat": 51.0748626, "lon": -4.2276896}, {"type": "node", "id": 1765376740, "lat": 51.0757795, "lon": -4.2299175}, {"type": "node", "id": 1765376742, "lat": 51.0753731, "lon": -4.2288509}, {"type": "node", "id": 1769664451, "lat": 51.1712452, "lon": -4.2091671}, {"type": "node", "id": 1769664743, "lat": 51.1759538, "lon": -4.2134318}, {"type": "node", "id": 1769888665, "lat": 51.1561068, "lon": -4.2129532}, {"type": "node", "id": 1777954907, "lat": 51.1821133, "lon": -4.2136338}, {"type": "node", "id": 1777954935, "lat": 51.1818214, "lon": -4.2145495}, {"type": "node", "id": 1777954947, "lat": 51.1763096, "lon": -4.2131494}, {"type": "node", "id": 1777954949, "lat": 51.1766257, "lon": -4.2140614}, {"type": "node", "id": 1777954951, "lat": 51.1819626, "lon": -4.2160623}, {"type": "node", "id": 1777954955, "lat": 51.1812867, "lon": -4.2166685}, {"type": "node", "id": 1777954957, "lat": 51.181623, "lon": -4.2154347}, {"type": "node", "id": 1777954964, "lat": 51.178125, "lon": -4.2114505}, {"type": "node", "id": 1777954967, "lat": 51.1822854, "lon": -4.2146515}, {"type": "node", "id": 1777954971, "lat": 51.1762087, "lon": -4.2135679}, {"type": "node", "id": 1777954975, "lat": 51.18204, "lon": -4.2150431}, {"type": "node", "id": 1777954980, "lat": 51.1815995, "lon": -4.2142599}, {"type": "node", "id": 1777954999, "lat": 51.1784194, "lon": -4.211646}, {"type": "node", "id": 1777955005, "lat": 51.1816768, "lon": -4.2136698}, {"type": "node", "id": 1777955011, "lat": 51.1821106, "lon": -4.2166524}, {"type": "node", "id": 1777955015, "lat": 51.1779501, "lon": -4.2117938}, {"type": "node", "id": 1777955016, "lat": 51.1824099, "lon": -4.214217}, {"type": "node", "id": 1777955031, "lat": 51.181354, "lon": -4.2160301}, {"type": "node", "id": 1777955044, "lat": 51.1759121, "lon": -4.2131564}, {"type": "node", "id": 1777955054, "lat": 51.1765114, "lon": -4.2141365}, {"type": "node", "id": 1777955060, "lat": 51.1819828, "lon": -4.2156224}, {"type": "node", "id": 1779438103, "lat": 51.1731353, "lon": -4.2123719}, {"type": "node", "id": 1779438141, "lat": 51.1728847, "lon": -4.2120828}, {"type": "node", "id": 1801881714, "lat": 51.0302579, "lon": -4.2034134}, {"type": "node", "id": 1801881715, "lat": 51.030431, "lon": -4.2033674}, {"type": "node", "id": 1912552538, "lat": 51.1166327, "lon": -4.2209386}, {"type": "node", "id": 1912552608, "lat": 51.1170341, "lon": -4.2211451}, {"type": "node", "id": 1912553490, "lat": 51.1336751, "lon": -4.2440633}, {"type": "node", "id": 1912675235, "lat": 51.1780684, "lon": -4.2123113}, {"type": "node", "id": 1912675243, "lat": 51.1782042, "lon": -4.2129638}, {"type": "node", "id": 1912675255, "lat": 51.1784922, "lon": -4.2121329}, {"type": "node", "id": 1962718382, "lat": 51.1622175, "lon": -4.6530299}, {"type": "node", "id": 1962718398, "lat": 51.1626302, "lon": -4.6524042}, {"type": "node", "id": 1962718400, "lat": 51.1627704, "lon": -4.6538313}, {"type": "node", "id": 1962718402, "lat": 51.1626491, "lon": -4.6533019}, {"type": "node", "id": 1962718405, "lat": 51.1627537, "lon": -4.6535193}, {"type": "node", "id": 1962718503, "lat": 51.1744221, "lon": -4.662658}, {"type": "node", "id": 1962718504, "lat": 51.1744594, "lon": -4.6627543}, {"type": "node", "id": 1962718506, "lat": 51.174557, "lon": -4.6629176}, {"type": "node", "id": 1962718507, "lat": 51.1746708, "lon": -4.6630784}, {"type": "node", "id": 1962718509, "lat": 51.1748258, "lon": -4.662768}, {"type": "node", "id": 1962718525, "lat": 51.1750739, "lon": -4.663125}, {"type": "node", "id": 1962718529, "lat": 51.1752495, "lon": -4.6630965}, {"type": "node", "id": 1962718531, "lat": 51.1753876, "lon": -4.6631665}, {"type": "node", "id": 1962718532, "lat": 51.1755979, "lon": -4.6629285}, {"type": "node", "id": 1978000010, "lat": 51.0658412, "lon": -4.188898}, {"type": "node", "id": 1978000016, "lat": 51.0659675, "lon": -4.1922349}, {"type": "node", "id": 1978000020, "lat": 51.0660831, "lon": -4.1897669}, {"type": "node", "id": 1978000025, "lat": 51.0661141, "lon": -4.1897093}, {"type": "node", "id": 1978000043, "lat": 51.0661588, "lon": -4.1900195}, {"type": "node", "id": 1978000050, "lat": 51.0661696, "lon": -4.1897173}, {"type": "node", "id": 1978000057, "lat": 51.0662372, "lon": -4.1897731}, {"type": "node", "id": 1978000061, "lat": 51.0662516, "lon": -4.1898731}, {"type": "node", "id": 1978000066, "lat": 51.0662774, "lon": -4.1899422}, {"type": "node", "id": 1978000068, "lat": 51.066308, "lon": -4.1906695}, {"type": "node", "id": 1978000070, "lat": 51.0663207, "lon": -4.1899851}, {"type": "node", "id": 1978000076, "lat": 51.067011, "lon": -4.188957}, {"type": "node", "id": 1978000095, "lat": 51.0670364, "lon": -4.1878788}, {"type": "node", "id": 1978000111, "lat": 51.067158, "lon": -4.1886773}, {"type": "node", "id": 1978000122, "lat": 51.0673933, "lon": -4.1884114}, {"type": "node", "id": 1978000127, "lat": 51.06754, "lon": -4.1877958}, {"type": "node", "id": 1978000134, "lat": 51.0676496, "lon": -4.1955451}, {"type": "node", "id": 1978000140, "lat": 51.0676675, "lon": -4.1884132}, {"type": "node", "id": 1978000178, "lat": 51.0677003, "lon": -4.188057}, {"type": "node", "id": 1978000346, "lat": 51.0709966, "lon": -4.2009709}, {"type": "node", "id": 2039645075, "lat": 51.0614394, "lon": -4.2363306}, {"type": "node", "id": 2039645077, "lat": 51.0621283, "lon": -4.2082277}, {"type": "node", "id": 2039645078, "lat": 51.062145, "lon": -4.2359297}, {"type": "node", "id": 2039645079, "lat": 51.0623257, "lon": -4.2084282}, {"type": "node", "id": 2039645081, "lat": 51.0626448, "lon": -4.2088224}, {"type": "node", "id": 2039645082, "lat": 51.062922, "lon": -4.2090964}, {"type": "node", "id": 2039645083, "lat": 51.0632664, "lon": -4.2097245}, {"type": "node", "id": 2039645085, "lat": 51.0633376, "lon": -4.235609}, {"type": "node", "id": 2039645094, "lat": 51.0636233, "lon": -4.2103258}, {"type": "node", "id": 2039645099, "lat": 51.0640263, "lon": -4.2352615}, {"type": "node", "id": 2039645103, "lat": 51.064291, "lon": -4.2112079}, {"type": "node", "id": 2039645115, "lat": 51.0646395, "lon": -4.2115487}, {"type": "node", "id": 2039645117, "lat": 51.0648999, "lon": -4.2119228}, {"type": "node", "id": 2039645121, "lat": 51.065198, "lon": -4.2120899}, {"type": "node", "id": 2039645123, "lat": 51.0653156, "lon": -4.2120765}, {"type": "node", "id": 2039645125, "lat": 51.0654836, "lon": -4.2121367}, {"type": "node", "id": 2039645128, "lat": 51.0656725, "lon": -4.2123705}, {"type": "node", "id": 2039645134, "lat": 51.0659077, "lon": -4.212591}, {"type": "node", "id": 2039645137, "lat": 51.0661259, "lon": -4.2348606}, {"type": "node", "id": 2039645140, "lat": 51.0665544, "lon": -4.2134129}, {"type": "node", "id": 2039645154, "lat": 51.0667643, "lon": -4.213747}, {"type": "node", "id": 2039645156, "lat": 51.0667853, "lon": -4.213894}, {"type": "node", "id": 2039645159, "lat": 51.0668777, "lon": -4.2140143}, {"type": "node", "id": 2039645165, "lat": 51.0670792, "lon": -4.2141346}, {"type": "node", "id": 2039645168, "lat": 51.0671169, "lon": -4.2348873}, {"type": "node", "id": 2039645172, "lat": 51.0673774, "lon": -4.2144152}, {"type": "node", "id": 2039645175, "lat": 51.0676587, "lon": -4.2147694}, {"type": "node", "id": 2039645184, "lat": 51.0679652, "lon": -4.2152371}, {"type": "node", "id": 2039645198, "lat": 51.068234, "lon": -4.2157516}, {"type": "node", "id": 2039645240, "lat": 51.0688596, "lon": -4.217215}, {"type": "node", "id": 2039645277, "lat": 51.0692879, "lon": -4.2185046}, {"type": "node", "id": 2039645306, "lat": 51.0700057, "lon": -4.2356891}, {"type": "node", "id": 2039645307, "lat": 51.0700185, "lon": -4.2196472}, {"type": "node", "id": 2039645310, "lat": 51.0702704, "lon": -4.2204557}, {"type": "node", "id": 2039645312, "lat": 51.0703752, "lon": -4.2355822}, {"type": "node", "id": 2039645315, "lat": 51.0705979, "lon": -4.2207297}, {"type": "node", "id": 2039645320, "lat": 51.0709758, "lon": -4.2207097}, {"type": "node", "id": 2039645327, "lat": 51.0712823, "lon": -4.2206362}, {"type": "node", "id": 2039645331, "lat": 51.0714837, "lon": -4.2358495}, {"type": "node", "id": 2039645332, "lat": 51.0714838, "lon": -4.2205426}, {"type": "node", "id": 2039645340, "lat": 51.0720211, "lon": -4.2360901}, {"type": "node", "id": 2039645341, "lat": 51.0720464, "lon": -4.2197809}, {"type": "node", "id": 2039645342, "lat": 51.0722073, "lon": -4.2197258}, {"type": "node", "id": 2039645344, "lat": 51.0723738, "lon": -4.2359564}, {"type": "node", "id": 2039645345, "lat": 51.0723962, "lon": -4.2197993}, {"type": "node", "id": 2039645347, "lat": 51.0726271, "lon": -4.2200131}, {"type": "node", "id": 2039645349, "lat": 51.0729013, "lon": -4.2354391}, {"type": "node", "id": 2039645350, "lat": 51.0729126, "lon": -4.2203472}, {"type": "node", "id": 2039645351, "lat": 51.0730762, "lon": -4.2355226}, {"type": "node", "id": 2039645353, "lat": 51.0732338, "lon": -4.2128762}, {"type": "node", "id": 2039645354, "lat": 51.0732737, "lon": -4.2209486}, {"type": "node", "id": 2039645355, "lat": 51.0733996, "lon": -4.2352156}, {"type": "node", "id": 2039645356, "lat": 51.073505, "lon": -4.2372027}, {"type": "node", "id": 2039645357, "lat": 51.0735159, "lon": -4.2354485}, {"type": "node", "id": 2039645358, "lat": 51.0735159, "lon": -4.2355194}, {"type": "node", "id": 2039645359, "lat": 51.0735344, "lon": -4.2372762}, {"type": "node", "id": 2039645360, "lat": 51.0735634, "lon": -4.2353966}, {"type": "node", "id": 2039645361, "lat": 51.0735865, "lon": -4.2347755}, {"type": "node", "id": 2039645362, "lat": 51.073602, "lon": -4.2356848}, {"type": "node", "id": 2039645363, "lat": 51.073618, "lon": -4.2216569}, {"type": "node", "id": 2039645364, "lat": 51.0736228, "lon": -4.2353918}, {"type": "node", "id": 2039645365, "lat": 51.073662, "lon": -4.2347746}, {"type": "node", "id": 2039645366, "lat": 51.0736688, "lon": -4.2373898}, {"type": "node", "id": 2039645367, "lat": 51.073697, "lon": -4.2354722}, {"type": "node", "id": 2039645368, "lat": 51.0737058, "lon": -4.2136274}, {"type": "node", "id": 2039645369, "lat": 51.0737415, "lon": -4.2358407}, {"type": "node", "id": 2039645370, "lat": 51.0737989, "lon": -4.2374633}, {"type": "node", "id": 2039645371, "lat": 51.0738573, "lon": -4.2355808}, {"type": "node", "id": 2039645372, "lat": 51.0738952, "lon": -4.2342085}, {"type": "node", "id": 2039645373, "lat": 51.0739078, "lon": -4.2348956}, {"type": "node", "id": 2039645374, "lat": 51.0739165, "lon": -4.2374833}, {"type": "node", "id": 2039645375, "lat": 51.0739197, "lon": -4.235973}, {"type": "node", "id": 2039645376, "lat": 51.0739371, "lon": -4.2227394}, {"type": "node", "id": 2039645377, "lat": 51.0739375, "lon": -4.2360202}, {"type": "node", "id": 2039645378, "lat": 51.0739427, "lon": -4.2340385}, {"type": "node", "id": 2039645379, "lat": 51.0739493, "lon": -4.23611}, {"type": "node", "id": 2039645380, "lat": 51.0739543, "lon": -4.2372829}, {"type": "node", "id": 2039645381, "lat": 51.0739731, "lon": -4.2362518}, {"type": "node", "id": 2039645382, "lat": 51.0739753, "lon": -4.2350213}, {"type": "node", "id": 2039645383, "lat": 51.0739962, "lon": -4.2352669}, {"type": "node", "id": 2039645384, "lat": 51.074, "lon": -4.2351689}, {"type": "node", "id": 2039645385, "lat": 51.0740057, "lon": -4.2356375}, {"type": "node", "id": 2039645386, "lat": 51.0740061, "lon": -4.2140098}, {"type": "node", "id": 2039645387, "lat": 51.0740117, "lon": -4.2363368}, {"type": "node", "id": 2039645388, "lat": 51.0740252, "lon": -4.2353225}, {"type": "node", "id": 2039645389, "lat": 51.0740634, "lon": -4.2372695}, {"type": "node", "id": 2039645390, "lat": 51.0740693, "lon": -4.2364008}, {"type": "node", "id": 2039645391, "lat": 51.0740923, "lon": -4.236689}, {"type": "node", "id": 2039645392, "lat": 51.0740978, "lon": -4.2357037}, {"type": "node", "id": 2039645393, "lat": 51.0741012, "lon": -4.2376504}, {"type": "node", "id": 2039645394, "lat": 51.0741049, "lon": -4.2367525}, {"type": "node", "id": 2039645395, "lat": 51.0741091, "lon": -4.2353693}, {"type": "node", "id": 2039645396, "lat": 51.0741209, "lon": -4.2339912}, {"type": "node", "id": 2039645397, "lat": 51.0741406, "lon": -4.2366021}, {"type": "node", "id": 2039645398, "lat": 51.074149, "lon": -4.2363716}, {"type": "node", "id": 2039645399, "lat": 51.0741981, "lon": -4.2354559}, {"type": "node", "id": 2039645400, "lat": 51.0742062, "lon": -4.2378375}, {"type": "node", "id": 2039645401, "lat": 51.0742121, "lon": -4.214679}, {"type": "node", "id": 2039645402, "lat": 51.0742225, "lon": -4.2357746}, {"type": "node", "id": 2039645403, "lat": 51.0742435, "lon": -4.236552}, {"type": "node", "id": 2039645404, "lat": 51.074254, "lon": -4.2363081}, {"type": "node", "id": 2039645405, "lat": 51.0742634, "lon": -4.234218}, {"type": "node", "id": 2039645406, "lat": 51.0742985, "lon": -4.2372361}, {"type": "node", "id": 2039645407, "lat": 51.0743026, "lon": -4.2358454}, {"type": "node", "id": 2039645408, "lat": 51.0743065, "lon": -4.2155667}, {"type": "node", "id": 2039645409, "lat": 51.0743274, "lon": -4.2363048}, {"type": "node", "id": 2039645410, "lat": 51.0743465, "lon": -4.2351724}, {"type": "node", "id": 2039645411, "lat": 51.074361, "lon": -4.236983}, {"type": "node", "id": 2039645412, "lat": 51.0743643, "lon": -4.23573}, {"type": "node", "id": 2039645413, "lat": 51.0743652, "lon": -4.2365119}, {"type": "node", "id": 2039645414, "lat": 51.0743653, "lon": -4.223902}, {"type": "node", "id": 2039645415, "lat": 51.0743947, "lon": -4.2359069}, {"type": "node", "id": 2039645416, "lat": 51.0744177, "lon": -4.2352953}, {"type": "node", "id": 2039645417, "lat": 51.0744245, "lon": -4.2372428}, {"type": "node", "id": 2039645418, "lat": 51.0744593, "lon": -4.2357678}, {"type": "node", "id": 2039645419, "lat": 51.0744702, "lon": -4.2363248}, {"type": "node", "id": 2039645420, "lat": 51.0744912, "lon": -4.2255592}, {"type": "node", "id": 2039645421, "lat": 51.0745015, "lon": -4.2358974}, {"type": "node", "id": 2039645422, "lat": 51.0745124, "lon": -4.2163315}, {"type": "node", "id": 2039645423, "lat": 51.0745187, "lon": -4.2347401}, {"type": "node", "id": 2039645424, "lat": 51.0745336, "lon": -4.2380179}, {"type": "node", "id": 2039645425, "lat": 51.0745365, "lon": -4.2355693}, {"type": "node", "id": 2039645426, "lat": 51.0745543, "lon": -4.2357111}, {"type": "node", "id": 2039645427, "lat": 51.0745625, "lon": -4.2371167}, {"type": "node", "id": 2039645428, "lat": 51.0745668, "lon": -4.2244366}, {"type": "node", "id": 2039645429, "lat": 51.0745793, "lon": -4.2366322}, {"type": "node", "id": 2039645430, "lat": 51.0745918, "lon": -4.2349273}, {"type": "node", "id": 2039645431, "lat": 51.0745919, "lon": -4.2362848}, {"type": "node", "id": 2039645432, "lat": 51.074592, "lon": -4.2260269}, {"type": "node", "id": 2039645433, "lat": 51.0745965, "lon": -4.2359021}, {"type": "node", "id": 2039645434, "lat": 51.0746325, "lon": -4.2169733}, {"type": "node", "id": 2039645435, "lat": 51.0746424, "lon": -4.2266684}, {"type": "node", "id": 2039645436, "lat": 51.0746434, "lon": -4.2350307}, {"type": "node", "id": 2039645437, "lat": 51.074657, "lon": -4.2362513}, {"type": "node", "id": 2039645438, "lat": 51.0746864, "lon": -4.2367224}, {"type": "node", "id": 2039645439, "lat": 51.0746886, "lon": -4.235836}, {"type": "node", "id": 2039645440, "lat": 51.074731, "lon": -4.2374499}, {"type": "node", "id": 2039645441, "lat": 51.0747767, "lon": -4.2271094}, {"type": "node", "id": 2039645442, "lat": 51.074787, "lon": -4.2176562}, {"type": "node", "id": 2039645443, "lat": 51.074831, "lon": -4.235836}, {"type": "node", "id": 2039645444, "lat": 51.0748522, "lon": -4.236375}, {"type": "node", "id": 2039645445, "lat": 51.074869, "lon": -4.2364585}, {"type": "node", "id": 2039645446, "lat": 51.074869, "lon": -4.2366055}, {"type": "node", "id": 2039645447, "lat": 51.074869, "lon": -4.2369062}, {"type": "node", "id": 2039645448, "lat": 51.0748779, "lon": -4.235026}, {"type": "node", "id": 2039645449, "lat": 51.0749131, "lon": -4.2366957}, {"type": "node", "id": 2039645450, "lat": 51.0749257, "lon": -4.2373071}, {"type": "node", "id": 2039645451, "lat": 51.0749347, "lon": -4.2351376}, {"type": "node", "id": 2039645452, "lat": 51.0749493, "lon": -4.2375034}, {"type": "node", "id": 2039645453, "lat": 51.0749677, "lon": -4.236953}, {"type": "node", "id": 2039645454, "lat": 51.0749937, "lon": -4.2354559}, {"type": "node", "id": 2039645455, "lat": 51.0750307, "lon": -4.2373906}, {"type": "node", "id": 2039645456, "lat": 51.0750386, "lon": -4.2374882}, {"type": "node", "id": 2039645457, "lat": 51.0750516, "lon": -4.2369296}, {"type": "node", "id": 2039645458, "lat": 51.0750542, "lon": -4.2381515}, {"type": "node", "id": 2039645459, "lat": 51.0750626, "lon": -4.2358738}, {"type": "node", "id": 2039645460, "lat": 51.0750649, "lon": -4.2355599}, {"type": "node", "id": 2039645461, "lat": 51.0750715, "lon": -4.2357793}, {"type": "node", "id": 2039645462, "lat": 51.0750804, "lon": -4.2360439}, {"type": "node", "id": 2039645463, "lat": 51.075081, "lon": -4.2367993}, {"type": "node", "id": 2039645464, "lat": 51.0751042, "lon": -4.2359541}, {"type": "node", "id": 2039645465, "lat": 51.075119, "lon": -4.2360202}, {"type": "node", "id": 2039645466, "lat": 51.0751428, "lon": -4.2357698}, {"type": "node", "id": 2039645467, "lat": 51.0751436, "lon": -4.2356284}, {"type": "node", "id": 2039645468, "lat": 51.0751658, "lon": -4.2356992}, {"type": "node", "id": 2039645469, "lat": 51.0751731, "lon": -4.2185439}, {"type": "node", "id": 2039645470, "lat": 51.0751798, "lon": -4.2283255}, {"type": "node", "id": 2039645471, "lat": 51.0755013, "lon": -4.2293213}, {"type": "node", "id": 2039645472, "lat": 51.0755593, "lon": -4.2190765}, {"type": "node", "id": 2039645473, "lat": 51.0755916, "lon": -4.2383854}, {"type": "node", "id": 2039645474, "lat": 51.0756315, "lon": -4.229495}, {"type": "node", "id": 2039645475, "lat": 51.0758393, "lon": -4.2384923}, {"type": "node", "id": 2039645476, "lat": 51.0759946, "lon": -4.2386059}, {"type": "node", "id": 2039645477, "lat": 51.0760261, "lon": -4.2386928}, {"type": "node", "id": 2039645478, "lat": 51.0760303, "lon": -4.2304372}, {"type": "node", "id": 2039645479, "lat": 51.0760655, "lon": -4.2197184}, {"type": "node", "id": 2039645480, "lat": 51.0760786, "lon": -4.2388364}, {"type": "node", "id": 2039645481, "lat": 51.0762528, "lon": -4.2310385}, {"type": "node", "id": 2039645482, "lat": 51.0762633, "lon": -4.2391872}, {"type": "node", "id": 2039645483, "lat": 51.0763229, "lon": -4.220333}, {"type": "node", "id": 2039645484, "lat": 51.0763683, "lon": -4.2392774}, {"type": "node", "id": 2039645485, "lat": 51.0764291, "lon": -4.231513}, {"type": "node", "id": 2039645486, "lat": 51.0766265, "lon": -4.2393309}, {"type": "node", "id": 2039645487, "lat": 51.0766391, "lon": -4.2319139}, {"type": "node", "id": 2039645488, "lat": 51.0767692, "lon": -4.2322547}, {"type": "node", "id": 2039645489, "lat": 51.0768553, "lon": -4.2392741}, {"type": "node", "id": 2039645490, "lat": 51.0768978, "lon": -4.2220674}, {"type": "node", "id": 2039645491, "lat": 51.0770952, "lon": -4.2226137}, {"type": "node", "id": 2039645492, "lat": 51.0771134, "lon": -4.2391505}, {"type": "node", "id": 2039645493, "lat": 51.0771344, "lon": -4.232963}, {"type": "node", "id": 2039645494, "lat": 51.0772373, "lon": -4.2391638}, {"type": "node", "id": 2039645495, "lat": 51.0773234, "lon": -4.2332503}, {"type": "node", "id": 2039645496, "lat": 51.0773674, "lon": -4.2392708}, {"type": "node", "id": 2039645497, "lat": 51.0774241, "lon": -4.2334975}, {"type": "node", "id": 2039645498, "lat": 51.0774556, "lon": -4.2393743}, {"type": "node", "id": 2039645499, "lat": 51.0775207, "lon": -4.2338249}, {"type": "node", "id": 2039645500, "lat": 51.0775396, "lon": -4.2394278}, {"type": "node", "id": 2039645501, "lat": 51.0776865, "lon": -4.2394979}, {"type": "node", "id": 2039645502, "lat": 51.0776886, "lon": -4.2342325}, {"type": "node", "id": 2039645503, "lat": 51.0777683, "lon": -4.2345332}, {"type": "node", "id": 2039645504, "lat": 51.0778901, "lon": -4.2348272}, {"type": "node", "id": 2039645505, "lat": 51.0780034, "lon": -4.2351613}, {"type": "node", "id": 2039645506, "lat": 51.078058, "lon": -4.2397251}, {"type": "node", "id": 2039645507, "lat": 51.0780622, "lon": -4.2354553}, {"type": "node", "id": 2039645508, "lat": 51.0782532, "lon": -4.2398788}, {"type": "node", "id": 2039645509, "lat": 51.0782721, "lon": -4.236197}, {"type": "node", "id": 2039645510, "lat": 51.0784484, "lon": -4.2367784}, {"type": "node", "id": 2039645511, "lat": 51.0784883, "lon": -4.2400292}, {"type": "node", "id": 2039645512, "lat": 51.0785281, "lon": -4.2247852}, {"type": "node", "id": 2039645513, "lat": 51.0785381, "lon": -4.2400053}, {"type": "node", "id": 2039645514, "lat": 51.078545, "lon": -4.2369989}, {"type": "node", "id": 2039645515, "lat": 51.0785828, "lon": -4.2372127}, {"type": "node", "id": 2039645516, "lat": 51.0786038, "lon": -4.2391505}, {"type": "node", "id": 2039645517, "lat": 51.0786415, "lon": -4.2389634}, {"type": "node", "id": 2039645518, "lat": 51.0786415, "lon": -4.2390502}, {"type": "node", "id": 2039645519, "lat": 51.0786457, "lon": -4.2393643}, {"type": "node", "id": 2039645520, "lat": 51.0787465, "lon": -4.2384355}, {"type": "node", "id": 2039645521, "lat": 51.0787885, "lon": -4.237921}, {"type": "node", "id": 2039645522, "lat": 51.0788095, "lon": -4.2382083}, {"type": "node", "id": 2039645523, "lat": 51.0791115, "lon": -4.2254817}, {"type": "node", "id": 2039645525, "lat": 51.0797464, "lon": -4.2264787}, {"type": "node", "id": 2039645527, "lat": 51.0805787, "lon": -4.2277624}, {"type": "node", "id": 2039645529, "lat": 51.0814195, "lon": -4.2296471}, {"type": "node", "id": 2039645530, "lat": 51.0815053, "lon": -4.2301797}, {"type": "node", "id": 2039645531, "lat": 51.0815825, "lon": -4.2304665}, {"type": "node", "id": 2039645532, "lat": 51.0823718, "lon": -4.2316957}, {"type": "node", "id": 2039645533, "lat": 51.082612, "lon": -4.2320576}, {"type": "node", "id": 2039645534, "lat": 51.0826657, "lon": -4.2321922}, {"type": "node", "id": 2039645535, "lat": 51.0828659, "lon": -4.2188247}, {"type": "node", "id": 2039645536, "lat": 51.0826957, "lon": -4.2323307}, {"type": "node", "id": 2039645537, "lat": 51.0827128, "lon": -4.2324516}, {"type": "node", "id": 2039645539, "lat": 51.0828136, "lon": -4.2325424}, {"type": "node", "id": 2039645540, "lat": 51.0828651, "lon": -4.2325322}, {"type": "node", "id": 2039645541, "lat": 51.083086, "lon": -4.2321122}, {"type": "node", "id": 2039645542, "lat": 51.0834213, "lon": -4.2191755}, {"type": "node", "id": 2039645543, "lat": 51.0832748, "lon": -4.2321239}, {"type": "node", "id": 2039645545, "lat": 51.0833734, "lon": -4.2321478}, {"type": "node", "id": 2039645546, "lat": 51.0834785, "lon": -4.2321054}, {"type": "node", "id": 2039645547, "lat": 51.0835171, "lon": -4.2320522}, {"type": "node", "id": 2039645548, "lat": 51.083545, "lon": -4.2317708}, {"type": "node", "id": 2039645549, "lat": 51.0835493, "lon": -4.23196}, {"type": "node", "id": 2039645550, "lat": 51.0835558, "lon": -4.2317176}, {"type": "node", "id": 2039645551, "lat": 51.0835751, "lon": -4.2318561}, {"type": "node", "id": 2039645552, "lat": 51.0835886, "lon": -4.2317071}, {"type": "node", "id": 2039645553, "lat": 51.083663, "lon": -4.2317859}, {"type": "node", "id": 2039645554, "lat": 51.0837359, "lon": -4.2321}, {"type": "node", "id": 2039645555, "lat": 51.0838206, "lon": -4.2326438}, {"type": "node", "id": 2039645556, "lat": 51.0838281, "lon": -4.2321648}, {"type": "node", "id": 2039645557, "lat": 51.0838343, "lon": -4.2327766}, {"type": "node", "id": 2039645558, "lat": 51.083854, "lon": -4.2322141}, {"type": "node", "id": 2039645559, "lat": 51.0838616, "lon": -4.2329408}, {"type": "node", "id": 2039645560, "lat": 51.0838752, "lon": -4.2322696}, {"type": "node", "id": 2039645561, "lat": 51.0838858, "lon": -4.2323203}, {"type": "node", "id": 2039645562, "lat": 51.0839237, "lon": -4.2329673}, {"type": "node", "id": 2039645563, "lat": 51.0839738, "lon": -4.2329577}, {"type": "node", "id": 2039645564, "lat": 51.0839768, "lon": -4.2326752}, {"type": "node", "id": 2039645565, "lat": 51.0839965, "lon": -4.2327525}, {"type": "node", "id": 2039645566, "lat": 51.0840102, "lon": -4.2326269}, {"type": "node", "id": 2039645567, "lat": 51.0840193, "lon": -4.2329094}, {"type": "node", "id": 2039645568, "lat": 51.0840269, "lon": -4.2328007}, {"type": "node", "id": 2039645569, "lat": 51.0840724, "lon": -4.2326052}, {"type": "node", "id": 2039645570, "lat": 51.0841558, "lon": -4.2327476}, {"type": "node", "id": 2039645571, "lat": 51.0842544, "lon": -4.2331073}, {"type": "node", "id": 2039645572, "lat": 51.0842877, "lon": -4.2331001}, {"type": "node", "id": 2039645573, "lat": 51.0843287, "lon": -4.2330011}, {"type": "node", "id": 2039645574, "lat": 51.0843635, "lon": -4.2329842}, {"type": "node", "id": 2039645575, "lat": 51.0843969, "lon": -4.2330229}, {"type": "node", "id": 2039645576, "lat": 51.08445, "lon": -4.2333777}, {"type": "node", "id": 2039645577, "lat": 51.084453, "lon": -4.2336192}, {"type": "node", "id": 2039645578, "lat": 51.0844682, "lon": -4.2338268}, {"type": "node", "id": 2039645579, "lat": 51.0844818, "lon": -4.2339499}, {"type": "node", "id": 2039645580, "lat": 51.0844985, "lon": -4.2352246}, {"type": "node", "id": 2039645581, "lat": 51.0845122, "lon": -4.2353526}, {"type": "node", "id": 2039645582, "lat": 51.0845561, "lon": -4.2351691}, {"type": "node", "id": 2039645583, "lat": 51.0845713, "lon": -4.2355192}, {"type": "node", "id": 2039645584, "lat": 51.0845834, "lon": -4.2350726}, {"type": "node", "id": 2039645585, "lat": 51.0846168, "lon": -4.2356037}, {"type": "node", "id": 2039645586, "lat": 51.0846274, "lon": -4.2350219}, {"type": "node", "id": 2039645587, "lat": 51.0846274, "lon": -4.2358668}, {"type": "node", "id": 2039645588, "lat": 51.0846289, "lon": -4.2345994}, {"type": "node", "id": 2039645589, "lat": 51.0846396, "lon": -4.2356447}, {"type": "node", "id": 2039645590, "lat": 51.0846426, "lon": -4.2346742}, {"type": "node", "id": 2039645591, "lat": 51.084723, "lon": -4.2360214}, {"type": "node", "id": 2039645592, "lat": 51.0847836, "lon": -4.2361372}, {"type": "node", "id": 2039645593, "lat": 51.0848261, "lon": -4.2362314}, {"type": "node", "id": 2039645594, "lat": 51.0848413, "lon": -4.2363714}, {"type": "node", "id": 2039645595, "lat": 51.0849125, "lon": -4.2366756}, {"type": "node", "id": 2039645596, "lat": 51.0849823, "lon": -4.236806}, {"type": "node", "id": 2039645597, "lat": 51.0849899, "lon": -4.2343241}, {"type": "node", "id": 2039645598, "lat": 51.0850051, "lon": -4.2343797}, {"type": "node", "id": 2039645599, "lat": 51.0850157, "lon": -4.2342686}, {"type": "node", "id": 2039645600, "lat": 51.0850521, "lon": -4.2342565}, {"type": "node", "id": 2039645601, "lat": 51.085137, "lon": -4.2343941}, {"type": "node", "id": 2039645602, "lat": 51.0851522, "lon": -4.2370088}, {"type": "node", "id": 2039645603, "lat": 51.0851764, "lon": -4.2344135}, {"type": "node", "id": 2039645604, "lat": 51.0852068, "lon": -4.2342638}, {"type": "node", "id": 2039645605, "lat": 51.0852068, "lon": -4.234399}, {"type": "node", "id": 2039645606, "lat": 51.0852083, "lon": -4.2347611}, {"type": "node", "id": 2039645607, "lat": 51.0852143, "lon": -4.2371198}, {"type": "node", "id": 2039645608, "lat": 51.0852234, "lon": -4.2342493}, {"type": "node", "id": 2039645609, "lat": 51.0852462, "lon": -4.2372719}, {"type": "node", "id": 2039645610, "lat": 51.0852522, "lon": -4.2375134}, {"type": "node", "id": 2039645611, "lat": 51.085272, "lon": -4.2376558}, {"type": "node", "id": 2039645612, "lat": 51.0853008, "lon": -4.2377693}, {"type": "node", "id": 2039645613, "lat": 51.085366, "lon": -4.2378779}, {"type": "node", "id": 2039645614, "lat": 51.0854479, "lon": -4.2379455}, {"type": "node", "id": 2039645615, "lat": 51.0854615, "lon": -4.2345704}, {"type": "node", "id": 2039645616, "lat": 51.0855176, "lon": -4.2379648}, {"type": "node", "id": 2039645617, "lat": 51.0855237, "lon": -4.2354347}, {"type": "node", "id": 2039645618, "lat": 51.0855631, "lon": -4.2379286}, {"type": "node", "id": 2039645619, "lat": 51.085595, "lon": -4.2378779}, {"type": "node", "id": 2039645620, "lat": 51.0856299, "lon": -4.2377982}, {"type": "node", "id": 2039645621, "lat": 51.085639, "lon": -4.2347466}, {"type": "node", "id": 2039645622, "lat": 51.0856845, "lon": -4.2377258}, {"type": "node", "id": 2039645623, "lat": 51.0857345, "lon": -4.2348794}, {"type": "node", "id": 2039645624, "lat": 51.0857846, "lon": -4.2377041}, {"type": "node", "id": 2039645625, "lat": 51.0858225, "lon": -4.2358596}, {"type": "node", "id": 2039645626, "lat": 51.0858361, "lon": -4.2350074}, {"type": "node", "id": 2039645627, "lat": 51.0858664, "lon": -4.2377113}, {"type": "node", "id": 2039645628, "lat": 51.0859104, "lon": -4.2351305}, {"type": "node", "id": 2039645629, "lat": 51.085918, "lon": -4.2377717}, {"type": "node", "id": 2039645630, "lat": 51.0860075, "lon": -4.2352971}, {"type": "node", "id": 2039645631, "lat": 51.0860151, "lon": -4.2379286}, {"type": "node", "id": 2039645632, "lat": 51.0860788, "lon": -4.2353719}, {"type": "node", "id": 2039645633, "lat": 51.0861288, "lon": -4.2382569}, {"type": "node", "id": 2039645634, "lat": 51.0861591, "lon": -4.2354516}, {"type": "node", "id": 2039645635, "lat": 51.0861986, "lon": -4.2383583}, {"type": "node", "id": 2039645636, "lat": 51.086235, "lon": -4.2362797}, {"type": "node", "id": 2039645637, "lat": 51.0862395, "lon": -4.2383825}, {"type": "node", "id": 2039645638, "lat": 51.0862547, "lon": -4.2356037}, {"type": "node", "id": 2039645639, "lat": 51.0862926, "lon": -4.2384066}, {"type": "node", "id": 2039645640, "lat": 51.0863108, "lon": -4.2356375}, {"type": "node", "id": 2039645641, "lat": 51.0863199, "lon": -4.2354299}, {"type": "node", "id": 2039645642, "lat": 51.0863335, "lon": -4.235553}, {"type": "node", "id": 2039645643, "lat": 51.0863502, "lon": -4.2354081}, {"type": "node", "id": 2039645644, "lat": 51.086373, "lon": -4.2354419}, {"type": "node", "id": 2039645645, "lat": 51.0864094, "lon": -4.2385877}, {"type": "node", "id": 2039645646, "lat": 51.0864321, "lon": -4.2355554}, {"type": "node", "id": 2039645647, "lat": 51.0864837, "lon": -4.2357437}, {"type": "node", "id": 2039645648, "lat": 51.0864912, "lon": -4.2387036}, {"type": "node", "id": 2039645649, "lat": 51.0865049, "lon": -4.2365718}, {"type": "node", "id": 2039645650, "lat": 51.0865231, "lon": -4.2358499}, {"type": "node", "id": 2039645651, "lat": 51.0865367, "lon": -4.2383318}, {"type": "node", "id": 2039645652, "lat": 51.0865398, "lon": -4.2382425}, {"type": "node", "id": 2039645653, "lat": 51.0865458, "lon": -4.2384646}, {"type": "node", "id": 2039645654, "lat": 51.086561, "lon": -4.2386601}, {"type": "node", "id": 2039645655, "lat": 51.0865625, "lon": -4.2358668}, {"type": "node", "id": 2039645656, "lat": 51.0865625, "lon": -4.2381604}, {"type": "node", "id": 2039645657, "lat": 51.086564, "lon": -4.2388533}, {"type": "node", "id": 2039645658, "lat": 51.0865656, "lon": -4.2387446}, {"type": "node", "id": 2039645659, "lat": 51.0865701, "lon": -4.2387036}, {"type": "node", "id": 2039645660, "lat": 51.0865716, "lon": -4.2376679}, {"type": "node", "id": 2039645661, "lat": 51.0865747, "lon": -4.238059}, {"type": "node", "id": 2039645662, "lat": 51.0865777, "lon": -4.2379479}, {"type": "node", "id": 2039645663, "lat": 51.0865792, "lon": -4.2388026}, {"type": "node", "id": 2039645664, "lat": 51.0865853, "lon": -4.2374844}, {"type": "node", "id": 2039645665, "lat": 51.0866141, "lon": -4.2355264}, {"type": "node", "id": 2039645666, "lat": 51.0866141, "lon": -4.2355892}, {"type": "node", "id": 2039645667, "lat": 51.0866429, "lon": -4.2356689}, {"type": "node", "id": 2039645668, "lat": 51.086652, "lon": -4.2371923}, {"type": "node", "id": 2039645669, "lat": 51.0866672, "lon": -4.2355313}, {"type": "node", "id": 2039645670, "lat": 51.0867005, "lon": -4.2357268}, {"type": "node", "id": 2039645671, "lat": 51.0867066, "lon": -4.237074}, {"type": "node", "id": 2039645672, "lat": 51.0867172, "lon": -4.2363738}, {"type": "node", "id": 2039645673, "lat": 51.0867915, "lon": -4.2363473}, {"type": "node", "id": 2039645674, "lat": 51.086793, "lon": -4.2369629}, {"type": "node", "id": 2039645675, "lat": 51.0868021, "lon": -4.2358451}, {"type": "node", "id": 2039645676, "lat": 51.0868355, "lon": -4.2359586}, {"type": "node", "id": 2039645677, "lat": 51.086837, "lon": -4.2358982}, {"type": "node", "id": 2039645678, "lat": 51.0868628, "lon": -4.2356182}, {"type": "node", "id": 2039645679, "lat": 51.0869098, "lon": -4.2363424}, {"type": "node", "id": 2039645680, "lat": 51.0869462, "lon": -4.2356133}, {"type": "node", "id": 2039645681, "lat": 51.0869856, "lon": -4.2367915}, {"type": "node", "id": 2039645682, "lat": 51.0869871, "lon": -4.2363714}, {"type": "node", "id": 2039645683, "lat": 51.0870296, "lon": -4.2355916}, {"type": "node", "id": 2039645684, "lat": 51.0870569, "lon": -4.2367408}, {"type": "node", "id": 2039645685, "lat": 51.0871615, "lon": -4.236468}, {"type": "node", "id": 2039645686, "lat": 51.0871646, "lon": -4.235483}, {"type": "node", "id": 2039645687, "lat": 51.0871646, "lon": -4.2367167}, {"type": "node", "id": 2039645688, "lat": 51.087207, "lon": -4.2366466}, {"type": "node", "id": 2039645689, "lat": 51.0872313, "lon": -4.2353695}, {"type": "node", "id": 2039645690, "lat": 51.0873208, "lon": -4.2352874}, {"type": "node", "id": 2039645691, "lat": 51.0874527, "lon": -4.2350581}, {"type": "node", "id": 2039645692, "lat": 51.0875725, "lon": -4.2347732}, {"type": "node", "id": 2039645693, "lat": 51.0877818, "lon": -4.2344448}, {"type": "node", "id": 2039645694, "lat": 51.0879486, "lon": -4.2341696}, {"type": "node", "id": 2039645695, "lat": 51.0881852, "lon": -4.2339982}, {"type": "node", "id": 2039645696, "lat": 51.0883535, "lon": -4.2338413}, {"type": "node", "id": 2039645697, "lat": 51.0886659, "lon": -4.233665}, {"type": "node", "id": 2039645698, "lat": 51.0890359, "lon": -4.2333633}, {"type": "node", "id": 2039645699, "lat": 51.0891739, "lon": -4.2332377}, {"type": "node", "id": 2039645700, "lat": 51.0894847, "lon": -4.2330711}, {"type": "node", "id": 2039645701, "lat": 51.0897865, "lon": -4.2329287}, {"type": "node", "id": 2039645702, "lat": 51.0902247, "lon": -4.2327018}, {"type": "node", "id": 2039645703, "lat": 51.0905219, "lon": -4.2326655}, {"type": "node", "id": 2039645704, "lat": 51.0910557, "lon": -4.2325086}, {"type": "node", "id": 2039645705, "lat": 51.0914302, "lon": -4.2324241}, {"type": "node", "id": 2039645706, "lat": 51.0917684, "lon": -4.2322817}, {"type": "node", "id": 2039645707, "lat": 51.0920307, "lon": -4.2322358}, {"type": "node", "id": 2039645708, "lat": 51.0922218, "lon": -4.232132}, {"type": "node", "id": 2039645709, "lat": 51.0924659, "lon": -4.232103}, {"type": "node", "id": 2039645710, "lat": 51.0928844, "lon": -4.2320885}, {"type": "node", "id": 2039645711, "lat": 51.0929708, "lon": -4.2321392}, {"type": "node", "id": 2039645712, "lat": 51.0930209, "lon": -4.2321392}, {"type": "node", "id": 2039645713, "lat": 51.0931361, "lon": -4.2320813}, {"type": "node", "id": 2039645714, "lat": 51.0940898, "lon": -4.2318326}, {"type": "node", "id": 2039645715, "lat": 51.0941573, "lon": -4.2220284, "tags": {"source": "PGS"}}, {"type": "node", "id": 2039645716, "lat": 51.0942657, "lon": -4.2317409}, {"type": "node", "id": 2039645717, "lat": 51.0946387, "lon": -4.231654}, {"type": "node", "id": 2039645718, "lat": 51.0948828, "lon": -4.2316878}, {"type": "node", "id": 2039645719, "lat": 51.095177, "lon": -4.2316805}, {"type": "node", "id": 2039645720, "lat": 51.0954044, "lon": -4.2316105}, {"type": "node", "id": 2039645723, "lat": 51.0961413, "lon": -4.2315695}, {"type": "node", "id": 2039645724, "lat": 51.0962095, "lon": -4.2314801}, {"type": "node", "id": 2039645725, "lat": 51.096493, "lon": -4.2314584}, {"type": "node", "id": 2039645726, "lat": 51.0966537, "lon": -4.2313908}, {"type": "node", "id": 2039645727, "lat": 51.0970858, "lon": -4.2313208}, {"type": "node", "id": 2039645728, "lat": 51.0973572, "lon": -4.2312967}, {"type": "node", "id": 2039645729, "lat": 51.0975043, "lon": -4.2313039}, {"type": "node", "id": 2039645730, "lat": 51.0978545, "lon": -4.2312991}, {"type": "node", "id": 2039645731, "lat": 51.0979925, "lon": -4.2313063}, {"type": "node", "id": 2039645732, "lat": 51.0981532, "lon": -4.2312315}, {"type": "node", "id": 2039645733, "lat": 51.0982487, "lon": -4.2311518}, {"type": "node", "id": 2039645734, "lat": 51.0983973, "lon": -4.2310939}, {"type": "node", "id": 2039645735, "lat": 51.0985474, "lon": -4.2311035}, {"type": "node", "id": 2039645736, "lat": 51.0992494, "lon": -4.2310311}, {"type": "node", "id": 2039645737, "lat": 51.0995329, "lon": -4.2309056}, {"type": "node", "id": 2039645738, "lat": 51.0997936, "lon": -4.2308476}, {"type": "node", "id": 2039645739, "lat": 51.1000893, "lon": -4.2308549}, {"type": "node", "id": 2039645740, "lat": 51.1003591, "lon": -4.2308211}, {"type": "node", "id": 2039645741, "lat": 51.1005941, "lon": -4.2307655}, {"type": "node", "id": 2039645743, "lat": 51.1007927, "lon": -4.2307462}, {"type": "node", "id": 2039645744, "lat": 51.1010065, "lon": -4.230751}, {"type": "node", "id": 2039645745, "lat": 51.1011171, "lon": -4.2307245}, {"type": "node", "id": 2039645746, "lat": 51.1012217, "lon": -4.2307969}, {"type": "node", "id": 2039645747, "lat": 51.1013779, "lon": -4.23085}, {"type": "node", "id": 2039645748, "lat": 51.1019024, "lon": -4.2308911}, {"type": "node", "id": 2039645749, "lat": 51.1020919, "lon": -4.2308331}, {"type": "node", "id": 2039645750, "lat": 51.1022754, "lon": -4.2307848}, {"type": "node", "id": 2039645751, "lat": 51.1026528, "lon": -4.2307221}, {"type": "node", "id": 2039645752, "lat": 51.1029773, "lon": -4.2306496}, {"type": "node", "id": 2039645753, "lat": 51.1037686, "lon": -4.2305555}, {"type": "node", "id": 2039645754, "lat": 51.1040763, "lon": -4.2305748}, {"type": "node", "id": 2039645755, "lat": 51.1045372, "lon": -4.2304855}, {"type": "node", "id": 2039645756, "lat": 51.1047524, "lon": -4.2305144}, {"type": "node", "id": 2039645757, "lat": 51.1049753, "lon": -4.2304879}, {"type": "node", "id": 2039645758, "lat": 51.1050374, "lon": -4.2304782}, {"type": "node", "id": 2039645759, "lat": 51.1051329, "lon": -4.2304179}, {"type": "node", "id": 2039645760, "lat": 51.1052163, "lon": -4.2304589}, {"type": "node", "id": 2039645761, "lat": 51.10538, "lon": -4.2304975}, {"type": "node", "id": 2039645762, "lat": 51.1055786, "lon": -4.2304637}, {"type": "node", "id": 2039645763, "lat": 51.1057953, "lon": -4.2303744}, {"type": "node", "id": 2039645764, "lat": 51.106191, "lon": -4.2303623}, {"type": "node", "id": 2039645765, "lat": 51.1064168, "lon": -4.2303189}, {"type": "node", "id": 2039645766, "lat": 51.1065851, "lon": -4.2302682}, {"type": "node", "id": 2039645767, "lat": 51.1071778, "lon": -4.2301861}, {"type": "node", "id": 2039645768, "lat": 51.1077705, "lon": -4.230063}, {"type": "node", "id": 2039645769, "lat": 51.1084541, "lon": -4.2298747}, {"type": "node", "id": 2039645770, "lat": 51.1086572, "lon": -4.229795}, {"type": "node", "id": 2039645771, "lat": 51.1089968, "lon": -4.2295777}, {"type": "node", "id": 2039645772, "lat": 51.1093484, "lon": -4.2294208}, {"type": "node", "id": 2039645773, "lat": 51.1094985, "lon": -4.2293749}, {"type": "node", "id": 2039645774, "lat": 51.1096394, "lon": -4.2292928}, {"type": "node", "id": 2039645775, "lat": 51.1102063, "lon": -4.2291866}, {"type": "node", "id": 2039645776, "lat": 51.1106337, "lon": -4.2291625}, {"type": "node", "id": 2039645777, "lat": 51.1110293, "lon": -4.2291818}, {"type": "node", "id": 2039645778, "lat": 51.1113643, "lon": -4.2292325}, {"type": "node", "id": 2039645779, "lat": 51.1115386, "lon": -4.2292011}, {"type": "node", "id": 2039645780, "lat": 51.1121904, "lon": -4.229008}, {"type": "node", "id": 2039645781, "lat": 51.1126769, "lon": -4.2290852}, {"type": "node", "id": 2039645782, "lat": 51.1129164, "lon": -4.2291069}, {"type": "node", "id": 2039645783, "lat": 51.1130482, "lon": -4.2290876}, {"type": "node", "id": 2039645784, "lat": 51.1133938, "lon": -4.2290128}, {"type": "node", "id": 2039645785, "lat": 51.1134802, "lon": -4.2290007}, {"type": "node", "id": 2039645786, "lat": 51.1135544, "lon": -4.2290369}, {"type": "node", "id": 2039645787, "lat": 51.1136484, "lon": -4.2291238}, {"type": "node", "id": 2039645788, "lat": 51.1139151, "lon": -4.2292083}, {"type": "node", "id": 2039645789, "lat": 51.1143153, "lon": -4.2292832}, {"type": "node", "id": 2039645790, "lat": 51.114626, "lon": -4.229329}, {"type": "node", "id": 2039645791, "lat": 51.1148957, "lon": -4.2292904}, {"type": "node", "id": 2039645792, "lat": 51.1151443, "lon": -4.2292252}, {"type": "node", "id": 2039645793, "lat": 51.1153019, "lon": -4.2292132}, {"type": "node", "id": 2039645794, "lat": 51.1157763, "lon": -4.2295149}, {"type": "node", "id": 2039645795, "lat": 51.11604, "lon": -4.2296067}, {"type": "node", "id": 2039645796, "lat": 51.1163097, "lon": -4.2296381}, {"type": "node", "id": 2039645797, "lat": 51.1170705, "lon": -4.2297878}, {"type": "node", "id": 2039645798, "lat": 51.1172979, "lon": -4.2299423}, {"type": "node", "id": 2039645799, "lat": 51.1175358, "lon": -4.2300702}, {"type": "node", "id": 2039645807, "lat": 51.1177131, "lon": -4.2302127}, {"type": "node", "id": 2039645836, "lat": 51.1178222, "lon": -4.2303961}, {"type": "node", "id": 2039645845, "lat": 51.1179965, "lon": -4.2306255}, {"type": "node", "id": 2039645859, "lat": 51.1181662, "lon": -4.2308645}, {"type": "node", "id": 2078485702, "lat": 51.1763358, "lon": -4.213225}, {"type": "node", "id": 2090996619, "lat": 51.0419449, "lon": -4.2391726}, {"type": "node", "id": 2090996620, "lat": 51.0418977, "lon": -4.2381805}, {"type": "node", "id": 2090996638, "lat": 51.0426516, "lon": -4.2374342}, {"type": "node", "id": 2090996643, "lat": 51.0428219, "lon": -4.237342}, {"type": "node", "id": 2090996648, "lat": 51.0429837, "lon": -4.2369523}, {"type": "node", "id": 2161415939, "lat": 51.0711127, "lon": -4.2033177}, {"type": "node", "id": 2161416082, "lat": 51.0987843, "lon": -4.2219208}, {"type": "node", "id": 2336976898, "lat": 51.1623251, "lon": -4.6532876}, {"type": "node", "id": 2336976901, "lat": 51.1623941, "lon": -4.6527996}, {"type": "node", "id": 2336976903, "lat": 51.1624332, "lon": -4.6525667}, {"type": "node", "id": 2336976904, "lat": 51.1624249, "lon": -4.6533243}, {"type": "node", "id": 2336976905, "lat": 51.1623975, "lon": -4.6517894}, {"type": "node", "id": 2336976909, "lat": 51.162489, "lon": -4.6534988}, {"type": "node", "id": 2336976915, "lat": 51.1625292, "lon": -4.6535255}, {"type": "node", "id": 2336976919, "lat": 51.1625436, "lon": -4.6534307}, {"type": "node", "id": 2336976922, "lat": 51.1625705, "lon": -4.6534343}, {"type": "node", "id": 2336976928, "lat": 51.1625908, "lon": -4.6534722}, {"type": "node", "id": 2336976929, "lat": 51.1625913, "lon": -4.6536706}, {"type": "node", "id": 2336976936, "lat": 51.1626869, "lon": -4.6539314}, {"type": "node", "id": 2336976937, "lat": 51.1626944, "lon": -4.6539844}, {"type": "node", "id": 2336976943, "lat": 51.1628493, "lon": -4.6535774}, {"type": "node", "id": 2449262350, "lat": 51.1176735, "lon": -4.2216125}, {"type": "node", "id": 2449262355, "lat": 51.1170671, "lon": -4.2211593}, {"type": "node", "id": 2449262357, "lat": 51.1172835, "lon": -4.2212846}, {"type": "node", "id": 2449289437, "lat": 51.0675786, "lon": -4.2249291}, {"type": "node", "id": 2449289438, "lat": 51.0660414, "lon": -4.2309158}, {"type": "node", "id": 2449289440, "lat": 51.0659403, "lon": -4.2206805}, {"type": "node", "id": 2449289442, "lat": 51.0660751, "lon": -4.2178695}, {"type": "node", "id": 2449289443, "lat": 51.0658257, "lon": -4.2215603}, {"type": "node", "id": 2449289444, "lat": 51.067911, "lon": -4.2237286}, {"type": "node", "id": 2449289445, "lat": 51.0660549, "lon": -4.2190819}, {"type": "node", "id": 2449289446, "lat": 51.0678301, "lon": -4.2269687}, {"type": "node", "id": 2449289447, "lat": 51.0661291, "lon": -4.2181163}, {"type": "node", "id": 2449289448, "lat": 51.067911, "lon": -4.2265824}, {"type": "node", "id": 2449289449, "lat": 51.0658324, "lon": -4.2205625}, {"type": "node", "id": 2449289450, "lat": 51.0662302, "lon": -4.2188888}, {"type": "node", "id": 2449289451, "lat": 51.0658324, "lon": -4.2194467}, {"type": "node", "id": 2449289452, "lat": 51.0658526, "lon": -4.2196291}, {"type": "node", "id": 2449289453, "lat": 51.0665087, "lon": -4.2299298}, {"type": "node", "id": 2449289454, "lat": 51.0676548, "lon": -4.2271403}, {"type": "node", "id": 2449289455, "lat": 51.0656908, "lon": -4.2204337}, {"type": "node", "id": 2449289456, "lat": 51.0657313, "lon": -4.2194145}, {"type": "node", "id": 2449289457, "lat": 51.0659605, "lon": -4.2190604}, {"type": "node", "id": 2449289458, "lat": 51.0658344, "lon": -4.2304663}, {"type": "node", "id": 2449289459, "lat": 51.0657131, "lon": -4.2325047}, {"type": "node", "id": 2449289460, "lat": 51.0660145, "lon": -4.2180305}, {"type": "node", "id": 2449289461, "lat": 51.0659673, "lon": -4.2206376}, {"type": "node", "id": 2449289462, "lat": 51.0660279, "lon": -4.2182236}, {"type": "node", "id": 2449289463, "lat": 51.0680728, "lon": -4.2251018}, {"type": "node", "id": 2449289464, "lat": 51.0653537, "lon": -4.2213993}, {"type": "node", "id": 2449289465, "lat": 51.0654616, "lon": -4.2214208}, {"type": "node", "id": 2449289466, "lat": 51.0654414, "lon": -4.2212491}, {"type": "node", "id": 2449289467, "lat": 51.0659133, "lon": -4.219275}, {"type": "node", "id": 2449289468, "lat": 51.0673177, "lon": -4.2256383}, {"type": "node", "id": 2449289469, "lat": 51.0656369, "lon": -4.2195218}, {"type": "node", "id": 2449289470, "lat": 51.067938, "lon": -4.2249731}, {"type": "node", "id": 2449289471, "lat": 51.0658998, "lon": -4.2200904}, {"type": "node", "id": 2449289473, "lat": 51.065722, "lon": -4.2349532}, {"type": "node", "id": 2449289475, "lat": 51.0658594, "lon": -4.2190604}, {"type": "node", "id": 2449289476, "lat": 51.067255, "lon": -4.2282121}, {"type": "node", "id": 2449289478, "lat": 51.0680593, "lon": -4.2241362}, {"type": "node", "id": 2449289480, "lat": 51.0680998, "lon": -4.2226342}, {"type": "node", "id": 2449289482, "lat": 51.0680101, "lon": -4.2229335}, {"type": "node", "id": 2449289483, "lat": 51.0672415, "lon": -4.2260234}, {"type": "node", "id": 2449289484, "lat": 51.0659066, "lon": -4.2213779}, {"type": "node", "id": 2449289485, "lat": 51.0657313, "lon": -4.2203586}, {"type": "node", "id": 2449289486, "lat": 51.0659066, "lon": -4.2203264}, {"type": "node", "id": 2449289487, "lat": 51.0668862, "lon": -4.2289213}, {"type": "node", "id": 2449289488, "lat": 51.0659334, "lon": -4.2349047}, {"type": "node", "id": 2449289489, "lat": 51.065821, "lon": -4.2338995}, {"type": "node", "id": 2449289490, "lat": 51.0682077, "lon": -4.2231063}, {"type": "node", "id": 2449289491, "lat": 51.0677357, "lon": -4.2243294}, {"type": "node", "id": 2449289492, "lat": 51.0656504, "lon": -4.2341774}, {"type": "node", "id": 2449289493, "lat": 51.0682346, "lon": -4.2237071}, {"type": "node", "id": 2449289494, "lat": 51.0666165, "lon": -4.2279557}, {"type": "node", "id": 2449289495, "lat": 51.0656571, "lon": -4.2205625}, {"type": "node", "id": 2449289496, "lat": 51.0657448, "lon": -4.2216139}, {"type": "node", "id": 2449289497, "lat": 51.0654076, "lon": -4.2208843}, {"type": "node", "id": 2449289498, "lat": 51.0681268, "lon": -4.2264751}, {"type": "node", "id": 2449289500, "lat": 51.065738, "lon": -4.2214744}, {"type": "node", "id": 2449289501, "lat": 51.0658864, "lon": -4.2208414}, {"type": "node", "id": 2449289502, "lat": 51.0660751, "lon": -4.2186742}, {"type": "node", "id": 2449289503, "lat": 51.0654211, "lon": -4.2215924}, {"type": "node", "id": 2449289504, "lat": 51.0653537, "lon": -4.2211418}, {"type": "node", "id": 2449289506, "lat": 51.0657852, "lon": -4.2191463}, {"type": "node", "id": 2449289507, "lat": 51.0660279, "lon": -4.2184811}, {"type": "node", "id": 2449289508, "lat": 51.067727, "lon": -4.2246502}, {"type": "node", "id": 2449289509, "lat": 51.0654346, "lon": -4.2210238}, {"type": "node", "id": 2449289510, "lat": 51.0658257, "lon": -4.220659}, {"type": "node", "id": 2449289511, "lat": 51.065738, "lon": -4.2213564}, {"type": "node", "id": 2449289512, "lat": 51.0679919, "lon": -4.2257241}, {"type": "node", "id": 2449289513, "lat": 51.0659153, "lon": -4.2320112}, {"type": "node", "id": 2449289514, "lat": 51.0680775, "lon": -4.2245858}, {"type": "node", "id": 2449289515, "lat": 51.0656908, "lon": -4.2207556}, {"type": "node", "id": 2449289516, "lat": 51.0660751, "lon": -4.2184167}, {"type": "node", "id": 2449289517, "lat": 51.0658998, "lon": -4.2210775}, {"type": "node", "id": 2449289518, "lat": 51.0653672, "lon": -4.2209702}, {"type": "node", "id": 2449289519, "lat": 51.0659875, "lon": -4.217891}, {"type": "node", "id": 2449289520, "lat": 51.0661763, "lon": -4.2184918}, {"type": "node", "id": 2449289521, "lat": 51.0656841, "lon": -4.2201226}, {"type": "node", "id": 2449289522, "lat": 51.0656234, "lon": -4.2203479}, {"type": "node", "id": 2449289523, "lat": 51.0661291, "lon": -4.2183201}, {"type": "node", "id": 2449289525, "lat": 51.0659201, "lon": -4.2198544}, {"type": "node", "id": 2449289526, "lat": 51.0679515, "lon": -4.2245225}, {"type": "node", "id": 2449289527, "lat": 51.0674795, "lon": -4.2275909}, {"type": "node", "id": 2449289528, "lat": 51.0655155, "lon": -4.2215924}, {"type": "node", "id": 2449289529, "lat": 51.0657717, "lon": -4.2211311}, {"type": "node", "id": 2449289530, "lat": 51.0657852, "lon": -4.2192536}, {"type": "node", "id": 2449289531, "lat": 51.0657785, "lon": -4.2209165}, {"type": "node", "id": 2451111257, "lat": 51.1160516, "lon": -4.2205807}, {"type": "node", "id": 2451111322, "lat": 51.0850285, "lon": -4.2206207}, {"type": "node", "id": 2451111341, "lat": 51.1168052, "lon": -4.2210737}, {"type": "node", "id": 2451111349, "lat": 51.1025861, "lon": -4.2217832}, {"type": "node", "id": 2451111379, "lat": 51.0879923, "lon": -4.2218046}, {"type": "node", "id": 2451111409, "lat": 51.1161051, "lon": -4.2203575}, {"type": "node", "id": 2451111425, "lat": 51.1168952, "lon": -4.2210153}, {"type": "node", "id": 2451129592, "lat": 51.1175307, "lon": -4.2238777}, {"type": "node", "id": 2451129606, "lat": 51.1180816, "lon": -4.2280904}, {"type": "node", "id": 2451129613, "lat": 51.1176029, "lon": -4.2241331}, {"type": "node", "id": 2451129618, "lat": 51.1181333, "lon": -4.2284849}, {"type": "node", "id": 2451129626, "lat": 51.1180407, "lon": -4.2274847}, {"type": "node", "id": 2451129627, "lat": 51.1180732, "lon": -4.227783}, {"type": "node", "id": 2451129635, "lat": 51.117621, "lon": -4.2224952}, {"type": "node", "id": 2451129636, "lat": 51.1179417, "lon": -4.2271135}, {"type": "node", "id": 3043749819, "lat": 51.1919654, "lon": -4.2076673}, {"type": "node", "id": 3043749820, "lat": 51.1927985, "lon": -4.20657}, {"type": "node", "id": 3043749821, "lat": 51.1925416, "lon": -4.2069721}, {"type": "node", "id": 3043749822, "lat": 51.1923746, "lon": -4.2074547}, {"type": "node", "id": 3043749823, "lat": 51.1921989, "lon": -4.2077832}, {"type": "node", "id": 3043749824, "lat": 51.1926293, "lon": -4.2068709}, {"type": "node", "id": 3043749825, "lat": 51.1922652, "lon": -4.2076912}, {"type": "node", "id": 3043749826, "lat": 51.1929342, "lon": -4.2065086}, {"type": "node", "id": 3043749827, "lat": 51.1937008, "lon": -4.2066081}, {"type": "node", "id": 3043749829, "lat": 51.193378, "lon": -4.2062056}, {"type": "node", "id": 3043749830, "lat": 51.1933457, "lon": -4.2059905}, {"type": "node", "id": 3043749831, "lat": 51.1918086, "lon": -4.2082092}, {"type": "node", "id": 3379299746, "lat": 51.1513085, "lon": -4.2158893}, {"type": "node", "id": 3379299751, "lat": 51.1514044, "lon": -4.2163999}, {"type": "node", "id": 3379299763, "lat": 51.1515289, "lon": -4.2167447}, {"type": "node", "id": 3379299773, "lat": 51.1516138, "lon": -4.2171069}, {"type": "node", "id": 3379299777, "lat": 51.1517383, "lon": -4.2175325}, {"type": "node", "id": 3379299778, "lat": 51.1517657, "lon": -4.2176023}, {"type": "node", "id": 3379299996, "lat": 51.1524309, "lon": -4.2200223}, {"type": "node", "id": 3379300002, "lat": 51.1525902, "lon": -4.2208138}, {"type": "node", "id": 3751402225, "lat": 51.1626472, "lon": -4.6517082}, {"type": "node", "id": 3751402226, "lat": 51.1622684, "lon": -4.6528944}, {"type": "node", "id": 3751402227, "lat": 51.1623262, "lon": -4.6528619}, {"type": "node", "id": 3906304050, "lat": 51.1444139, "lon": -4.225456}, {"type": "node", "id": 3906304661, "lat": 51.1455828, "lon": -4.2212122}, {"type": "node", "id": 4279001324, "lat": 51.1299159, "lon": -4.2437272}, {"type": "node", "id": 4279001326, "lat": 51.133598, "lon": -4.2390639}, {"type": "node", "id": 4279001327, "lat": 51.1309992, "lon": -4.2436987}, {"type": "node", "id": 4279013385, "lat": 51.1785355, "lon": -4.2128131}, {"type": "node", "id": 4827353565, "lat": 51.085644, "lon": -4.2209332}, {"type": "node", "id": 4827353569, "lat": 51.0946179, "lon": -4.2220344}, {"type": "node", "id": 5696121233, "lat": 51.1780533, "lon": -4.2115912}, {"type": "node", "id": 5809013849, "lat": 51.1727917, "lon": -4.2098161}, {"type": "node", "id": 5809013850, "lat": 51.1726155, "lon": -4.2091057}, {"type": "node", "id": 5913356229, "lat": 51.1923804, "lon": -4.2073978}, {"type": "node", "id": 6684839364, "lat": 51.1526248, "lon": -4.2146307}, {"type": "node", "id": 7240921172, "lat": 51.1339421, "lon": -4.2450571}, {"type": "node", "id": 7240921173, "lat": 51.1325821, "lon": -4.2445314}, {"type": "node", "id": 7747822176, "lat": 51.1327218, "lon": -4.2377561}, {"type": "node", "id": 7747822178, "lat": 51.133291, "lon": -4.2384433}, {"type": "node", "id": 7747822179, "lat": 51.1332303, "lon": -4.238324}, {"type": "node", "id": 7747822180, "lat": 51.133213, "lon": -4.2382236}, {"type": "node", "id": 7747822181, "lat": 51.1331963, "lon": -4.2380297}, {"type": "node", "id": 7747822182, "lat": 51.1332047, "lon": -4.2377822}, {"type": "node", "id": 7747822183, "lat": 51.1332582, "lon": -4.2374216}, {"type": "node", "id": 7747822184, "lat": 51.1333433, "lon": -4.2374314}, {"type": "node", "id": 7747833285, "lat": 51.1333045, "lon": -4.2374816}, {"type": "node", "id": 7747833286, "lat": 51.133245, "lon": -4.2376281}, {"type": "node", "id": 7747833287, "lat": 51.1332276, "lon": -4.2376751}, {"type": "node", "id": 7747833552, "lat": 51.1334125, "lon": -4.238657}, {"type": "node", "id": 7747833553, "lat": 51.1334867, "lon": -4.2387677}, {"type": "node", "id": 9060407647, "lat": 51.0429538, "lon": -4.2367789}, {"type": "node", "id": 9060407649, "lat": 51.0421345, "lon": -4.2404151}, {"type": "node", "id": 9105370290, "lat": 51.1701201, "lon": -4.2092124}, {"type": "node", "id": 10169117521, "lat": 51.1009449, "lon": -4.2218001}, {"type": "node", "id": 10221917396, "lat": 51.1698419, "lon": -4.2094427}, {"type": "node", "id": 10221917397, "lat": 51.170243, "lon": -4.2090578}, {"type": "node", "id": 10221917398, "lat": 51.1703557, "lon": -4.2088473}, {"type": "node", "id": 10221917399, "lat": 51.1722096, "lon": -4.2092069}, {"type": "node", "id": 10221917400, "lat": 51.171638, "lon": -4.2092308}, {"type": "node", "id": 10221917402, "lat": 51.1725705, "lon": -4.2089653}, {"type": "node", "id": 10221917419, "lat": 51.1706561, "lon": -4.2085221}, {"type": "node", "id": 10572995737, "lat": 51.1453022, "lon": -4.221739}, {"type": "node", "id": 10748990290, "lat": 51.1333085, "lon": -4.238474}, {"type": "node", "id": 10751276163, "lat": 51.1512444, "lon": -4.2154375}, {"type": "node", "id": 10751276164, "lat": 51.1507497, "lon": -4.2161295}, {"type": "node", "id": 10751276165, "lat": 51.1512544, "lon": -4.2158344}, {"type": "node", "id": 10753903687, "lat": 51.176297, "lon": -4.2131335}, {"type": "node", "id": 10753903688, "lat": 51.1762709, "lon": -4.2130369}, {"type": "node", "id": 10753903689, "lat": 51.1762759, "lon": -4.2129001}, {"type": "node", "id": 10753903690, "lat": 51.1762743, "lon": -4.2128035}, {"type": "node", "id": 10753903691, "lat": 51.1762154, "lon": -4.2128009}, {"type": "node", "id": 10753903692, "lat": 51.1761481, "lon": -4.2127915}, {"type": "node", "id": 10753903693, "lat": 51.1760943, "lon": -4.2127901}, {"type": "node", "id": 10753903694, "lat": 51.1760136, "lon": -4.2128344}, {"type": "node", "id": 10753903695, "lat": 51.1759422, "lon": -4.212935}, {"type": "node", "id": 10773907711, "lat": 51.1171417, "lon": -4.2212498}, {"type": "node", "id": 10773951772, "lat": 51.1171205, "lon": -4.2212241}, {"type": "node", "id": 11134227022, "lat": 51.1723081, "lon": -4.2090446}, {"type": "node", "id": 11134227024, "lat": 51.1706009, "lon": -4.2084553}, {"type": "node", "id": 11134525283, "lat": 51.1662813, "lon": -4.2102197}, {"type": "node", "id": 11155851406, "lat": 51.0302646, "lon": -4.2035544}, {"type": "node", "id": 11155851407, "lat": 51.030542, "lon": -4.203312}, {"type": "node", "id": 11155851408, "lat": 51.0305194, "lon": -4.2034005}, {"type": "node", "id": 11156524123, "lat": 51.0600536, "lon": -4.2162989}, {"type": "node", "id": 11156524124, "lat": 51.0602076, "lon": -4.217539}, {"type": "node", "id": 11156524125, "lat": 51.0607881, "lon": -4.2183096}, {"type": "node", "id": 11156524127, "lat": 51.0611025, "lon": -4.2187639}, {"type": "node", "id": 11156524128, "lat": 51.0602085, "lon": -4.2186159}, {"type": "node", "id": 11156524129, "lat": 51.0592687, "lon": -4.2176411}, {"type": "node", "id": 11156524130, "lat": 51.0591276, "lon": -4.2166918}, {"type": "node", "id": 11156524131, "lat": 51.0589094, "lon": -4.2154057}, {"type": "node", "id": 11156524132, "lat": 51.0589447, "lon": -4.2152067}, {"type": "node", "id": 11156524134, "lat": 51.0592751, "lon": -4.2152118}, {"type": "node", "id": 11156524135, "lat": 51.0596247, "lon": -4.2157375}, {"type": "node", "id": 11156524137, "lat": 51.0598365, "lon": -4.2157834}, {"type": "node", "id": 11156524138, "lat": 51.0592619, "lon": -4.2149617}, {"type": "node", "id": 11156524139, "lat": 51.059634, "lon": -4.2154159}, {"type": "node", "id": 11156524140, "lat": 51.0604838, "lon": -4.2175948}, {"type": "node", "id": 11156524141, "lat": 51.0587788, "lon": -4.2156405}, {"type": "node", "id": 11156524142, "lat": 51.0588205, "lon": -4.2159773}, {"type": "node", "id": 11156524143, "lat": 51.0589873, "lon": -4.2169011}, {"type": "node", "id": 11156524144, "lat": 51.0589048, "lon": -4.2178519}, {"type": "node", "id": 11156524145, "lat": 51.060007, "lon": -4.2189703}, {"type": "node", "id": 11156524146, "lat": 51.0608192, "lon": -4.218897}, {"type": "node", "id": 11156524147, "lat": 51.0591847, "lon": -4.2151773}, {"type": "node", "id": 11156524149, "lat": 51.0618443, "lon": -4.2086263}, {"type": "node", "id": 11156524171, "lat": 51.0619785, "lon": -4.2088553}, {"type": "node", "id": 11156524183, "lat": 51.0625781, "lon": -4.2100336}, {"type": "node", "id": 11156524185, "lat": 51.0621706, "lon": -4.2092386}, {"type": "node", "id": 12219282554, "lat": 51.1708865, "lon": -4.2089123}, {"type": "node", "id": 12219283907, "lat": 51.1703988, "lon": -4.2087055}, {"type": "node", "id": 12219283908, "lat": 51.1689782, "lon": -4.2097402}, {"type": "node", "id": 12219283909, "lat": 51.1671792, "lon": -4.2100631}, {"type": "node", "id": 12219283910, "lat": 51.1667628, "lon": -4.210104}, {"type": "node", "id": 12219283911, "lat": 51.1658943, "lon": -4.2103334}, {"type": "node", "id": 12219283912, "lat": 51.1645682, "lon": -4.2106447}, {"type": "node", "id": 12219283913, "lat": 51.16337, "lon": -4.2109171}, {"type": "node", "id": 12219283914, "lat": 51.1622443, "lon": -4.2111381}, {"type": "node", "id": 12219283915, "lat": 51.1609986, "lon": -4.2114483}, {"type": "node", "id": 12219283916, "lat": 51.1594348, "lon": -4.2118646}, {"type": "node", "id": 12219283917, "lat": 51.1584992, "lon": -4.2121268}, {"type": "node", "id": 12219283918, "lat": 51.1581022, "lon": -4.2122682}, {"type": "node", "id": 12219283919, "lat": 51.1572534, "lon": -4.2125101}, {"type": "node", "id": 12219283920, "lat": 51.155699, "lon": -4.2131427}, {"type": "node", "id": 12219283921, "lat": 51.1529182, "lon": -4.2144641}, {"type": "node", "id": 12219283922, "lat": 51.1521702, "lon": -4.214861}, {"type": "node", "id": 12219283923, "lat": 51.1518686, "lon": -4.2150507}, {"type": "node", "id": 12219283924, "lat": 51.1515359, "lon": -4.21526}, {"type": "node", "id": 12219283996, "lat": 51.1463257, "lon": -4.2196563}, {"type": "node", "id": 12219284002, "lat": 51.1474748, "lon": -4.2186323}, {"type": "node", "id": 12219284003, "lat": 51.1472114, "lon": -4.2187797}, {"type": "node", "id": 12219284004, "lat": 51.1469526, "lon": -4.2190779}, {"type": "node", "id": 12219284048, "lat": 51.1456101, "lon": -4.2209337}, {"type": "node", "id": 12219284049, "lat": 51.1457997, "lon": -4.220378}, {"type": "node", "id": 12219284178, "lat": 51.1526026, "lon": -4.2208561}, {"type": "way", "id": 23121779, "nodes": [10751276165, 10751276163, 320377311, 12219283924, 12219283923, 12219283922, 6684839364, 12219283921, 320377313, 48961735, 320377315, 12219283920, 320377316, 1769888665, 320377317, 12219283919, 320377319, 12219283918, 12219283917, 320377320, 12219283916, 48961716, 12219283915, 12219283914, 12219283913, 12219283912, 320377321, 12219283911, 11134525283, 12219283910, 12219283909, 48961738, 320377324, 12219283908, 48961745, 10221917396, 9105370290, 10221917397, 10221917398, 12219283907, 325192187, 325192426, 325192427, 11134227024, 325192428, 10221917419, 325192430, 12219282554, 1769664451, 10221917400, 10221917399, 11134227022, 10221917402, 5809013850, 5809013849, 20984574, 20984572, 20984570, 1779438141, 1779438103, 48961710, 249630258, 249630259, 249630260, 249630261, 699784242, 249630262, 12219284178, 3379300002, 3379299996, 3379299778, 3379299777, 3379299773, 3379299763, 3379299751, 3379299746, 10751276165], "tags": {"foot": "yes", "image": "https://archive.org/details/lee-2021-09-06/PXL_20210906_141916444.jpg", "name": "Woolacombe Sands", "natural": "beach", "operator": "Parkin Estates", "sport": "surfing;swimming", "surface": "sand", "vehicle": "no", "website": "https://www.parkinestates.co.uk/"}}, {"type": "way", "id": 55692013, "nodes": [699784302, 3043749831, 3043749819, 699784301, 3043749823, 3043749825, 3043749822, 5913356229, 699784317, 699784316, 3043749821, 3043749824, 699784315, 3043749820, 3043749826, 699784322, 699784321, 3043749830, 3043749829, 699784327, 699784320, 3043749827, 699784335, 1764178361, 1764178520, 1764178436, 699784338, 699784308, 699784302], "tags": {"name": "Rockham Beach", "natural": "beach", "source": "gps survey"}}, {"type": "way", "id": 68641733, "nodes": [825156635, 825156638, 825156639, 825156641, 825156644, 825156647, 825156648, 825156651, 825156654, 825156656, 825156658, 825156667, 825156670, 825156812, 825156672, 825156676, 825156679, 825156680, 825156681, 825156682, 825156683, 825156684, 825156685, 825156688, 825156691, 825156696, 825156700, 825156703, 825156704, 825156706, 825156708, 825156712, 825156722, 825156723, 825156635], "tags": {"name": "Pulley Ridge", "natural": "beach", "source": "OS OpenData StreetView", "tidal": "yes"}}, {"type": "way", "id": 151234392, "nodes": [2090996638, 2090996620, 2090996619, 9060407649, 1640545806, 1640545834, 1640545873, 1640545880, 1640546164, 1640546247, 1640546321, 1640546416, 1640546434, 1640546438, 1640546442, 1640546444, 1640546445, 1640686197, 1640686198, 1640686194, 1640686184, 1640686178, 1640686173, 1640686167, 1640686164, 11156524149, 11156524171, 11156524185, 1640686166, 11156524183, 1640686171, 1640686180, 1640686189, 1640686191, 1640686193, 1692199638, 1640686196, 1692199640, 1640686195, 1640546443, 1640686192, 1640546440, 1640546439, 1692199636, 1640546432, 1640546430, 1640546427, 1640546413, 1640546383, 1640546327, 1640546268, 1692199627, 1692199626, 1640546072, 1640546010, 1640545911, 1692199606, 1640545879, 1640545876, 1640545835, 1640545830, 9060407647, 2090996648, 2090996643, 2090996638], "tags": {"name": "Northam Beach", "natural": "beach", "surface": "sand", "tidal": "yes"}}, {"type": "way", "id": 166342927, "nodes": [1777955011, 1777954955, 1777955031, 1777954957, 1777954935, 1777954980, 1777955005, 1777954907, 1777955016, 1777954967, 1777954975, 1777955060, 1777954951, 1777955011], "tags": {"name": "Grunta Beach", "natural": "beach"}}, {"type": "way", "id": 166342929, "nodes": [1777954947, 10753903687, 10753903688, 10753903689, 10753903690, 10753903691, 10753903692, 10753903693, 10753903694, 10753903695, 1777955044, 1769664743, 1777954971, 1777955054, 1777954949, 2078485702, 1777954947], "tags": {"description": "Site of Special Scientific Interest with\u00a0400 million year old Morte Slate. Small Cowrie shells can be found here.", "name": "Barricane Beach (SSSI)", "natural": "beach"}}, {"type": "way", "id": 166342934, "nodes": [1912675235, 1777955015, 5696121233, 1777954964, 1777954999, 1912675255, 4279013385, 1912675243, 1912675235], "tags": {"name": "Combesgate Beach", "natural": "beach"}}, {"type": "way", "id": 185626892, "nodes": [1962718532, 1962718531, 1962718529, 1962718525, 1962718507, 1962718506, 1962718504, 1962718503, 1962718509, 1962718532], "tags": {"name": "Quarry Beach", "natural": "beach"}}, {"type": "way", "id": 185626919, "nodes": [1962718405, 2336976943, 1962718400, 2336976937, 2336976936, 2336976929, 2336976928, 2336976922, 2336976919, 2336976915, 2336976909, 2336976904, 2336976898, 1962718382, 3751402226, 3751402227, 2336976901, 2336976903, 2336976905, 3751402225, 1962718398, 1962718402, 1962718405], "tags": {"name": "Devil's Kitchen", "natural": "beach", "surface": "Rock_pools"}}, {"type": "way", "id": 236970692, "nodes": [2039645575, 2039645608, 2039645604, 2039645605, 2039645603, 2039645601, 2039645600, 2039645599, 2039645597, 2039645598, 2039645606, 2039645617, 2039645625, 2039645636, 2039645649, 2039645672, 2039645673, 2039645679, 2039645682, 2039645685, 2039645688, 2039645687, 2039645684, 2039645681, 2039645674, 2039645671, 2039645668, 2039645664, 2039645660, 2039645662, 2039645661, 2039645656, 2039645652, 2039645651, 2039645653, 2039645654, 2039645659, 2039645658, 2039645663, 2039645657, 2039645648, 2039645645, 2039645639, 2039645637, 2039645635, 2039645633, 2039645631, 2039645629, 2039645627, 2039645624, 2039645622, 2039645620, 2039645619, 2039645618, 2039645616, 2039645614, 2039645613, 2039645612, 2039645611, 2039645610, 2039645609, 2039645607, 2039645602, 2039645596, 2039645595, 2039645594, 2039645593, 2039645592, 2039645591, 2039645587, 2039645589, 2039645585, 2039645583, 2039645581, 2039645580, 2039645582, 2039645584, 2039645586, 2039645590, 2039645588, 2039645579, 2039645578, 2039645577, 2039645576, 2039645575], "tags": {"name": "North Tail", "natural": "beach"}}, {"type": "way", "id": 236970693, "nodes": [1978000140, 1978000122, 1978000111, 1978000076, 1978000070, 1978000066, 1978000061, 1978000057, 1978000050, 1978000025, 1978000020, 1978000043, 1978000068, 320375123, 320375124, 320375125, 224705204, 320375127, 1978000346, 320375129, 2161415939, 320375131, 224705205, 320375132, 320375134, 224705207, 320375135, 320374029, 320374030, 320374031, 320374035, 224705211, 320374036, 320374037, 320374038, 320374039, 2039645535, 2039645542, 320374040, 1561249480, 2451111322, 4827353565, 320373106, 320373108, 2451111379, 1561249582, 1561249485, 2039645715, 4827353569, 1298613934, 320373112, 2161416082, 320373116, 10169117521, 2451111349, 1561249527, 320373117, 320373118, 320373119, 320373120, 320373121, 1561249569, 1561249536, 1561249503, 320372492, 320372494, 224705223, 2451111257, 2451111409, 1561249487, 1912552538, 320372496, 2451111341, 2451111425, 1912552608, 2449262355, 10773951772, 10773907711, 2449262357, 224705224, 2449262350, 320372497, 2451129635, 320372498, 320372499, 2451129592, 2451129613, 320372500, 320372501, 320372229, 224705225, 2451129636, 2451129626, 2451129627, 2451129606, 2451129618, 320372230, 320372231, 320372232, 224705181, 2039645859, 2039645845, 2039645836, 2039645807, 2039645799, 2039645798, 2039645797, 2039645796, 2039645795, 2039645794, 2039645793, 2039645792, 2039645791, 2039645790, 2039645789, 2039645788, 2039645787, 2039645786, 2039645785, 2039645784, 2039645783, 2039645782, 2039645781, 2039645780, 2039645779, 2039645778, 2039645777, 2039645776, 2039645775, 2039645774, 2039645773, 2039645772, 2039645771, 2039645770, 2039645769, 2039645768, 2039645767, 2039645766, 2039645765, 2039645764, 2039645763, 2039645762, 2039645761, 2039645760, 2039645759, 2039645758, 2039645757, 2039645756, 2039645755, 2039645754, 2039645753, 2039645752, 2039645751, 2039645750, 2039645749, 2039645748, 2039645747, 2039645746, 2039645745, 2039645744, 2039645743, 2039645741, 2039645740, 2039645739, 2039645738, 2039645737, 2039645736, 2039645735, 2039645734, 2039645733, 2039645732, 2039645731, 2039645730, 2039645729, 2039645728, 2039645727, 2039645726, 2039645725, 2039645724, 2039645723, 2039645720, 2039645719, 2039645718, 2039645717, 2039645716, 2039645714, 2039645713, 2039645712, 2039645711, 2039645710, 2039645709, 2039645708, 2039645707, 2039645706, 2039645705, 2039645704, 2039645703, 2039645702, 2039645701, 2039645700, 2039645699, 2039645698, 2039645697, 2039645696, 2039645695, 2039645694, 2039645693, 2039645692, 2039645691, 2039645690, 2039645689, 2039645686, 2039645683, 2039645680, 2039645678, 2039645669, 2039645665, 2039645666, 2039645667, 2039645670, 2039645675, 2039645677, 2039645676, 2039645655, 2039645650, 2039645647, 2039645646, 2039645644, 2039645643, 2039645641, 2039645642, 2039645640, 2039645638, 2039645634, 2039645632, 2039645630, 2039645628, 2039645626, 2039645623, 2039645621, 2039645615, 2039645608, 2039645575, 2039645574, 2039645573, 2039645572, 2039645571, 2039645570, 2039645569, 2039645566, 2039645564, 2039645565, 2039645568, 2039645567, 2039645563, 2039645562, 2039645559, 2039645557, 2039645555, 2039645561, 2039645560, 2039645558, 2039645556, 2039645554, 2039645553, 2039645552, 2039645550, 2039645548, 2039645551, 2039645549, 2039645547, 2039645546, 2039645545, 2039645543, 2039645541, 2039645540, 2039645539, 2039645537, 2039645536, 2039645534, 2039645533, 2039645532, 2039645531, 2039645530, 2039645529, 2039645527, 2039645525, 2039645523, 2039645512, 2039645491, 2039645490, 2039645483, 2039645479, 2039645472, 2039645469, 2039645442, 2039645434, 2039645422, 2039645408, 2039645401, 2039645386, 2039645368, 2039645353]}, {"type": "way", "id": 236975502, "nodes": [2449289473, 2449289492, 2449289459, 2449289458, 2449289494, 2449289483, 2449289468, 2449289437, 2449289508, 2449289491, 2449289444, 2449289482, 2449289480, 2449289490, 2449289493, 2449289478, 2449289526, 2449289514, 2449289470, 2449289463, 2449289512, 2449289498, 2449289448, 2449289446, 2449289454, 2449289527, 2449289476, 2449289487, 2449289453, 2449289438, 2449289513, 2449289489, 2449289488, 2039645137, 2039645168, 1765376731, 2039645306, 2039645312, 2039645331, 2039645340, 2039645344, 2039645349, 2039645351, 2039645355, 2039645361, 2039645365, 2039645373, 2039645382, 2039645384, 2039645383, 2039645388, 2039645395, 2039645399, 2039645412, 2039645418, 2039645426, 2039645425, 2039645416, 2039645410, 2039645372, 2039645378, 2039645481, 2039645478, 1765376740, 2039645474, 2039645471, 1765376742, 2039645470, 1765376738, 2039645441, 2039645435, 2039645432, 2039645420, 2039645428, 2039645414, 2039645376, 2039645363, 2039645354, 2039645350, 2039645347, 2039645345, 2039645342, 2039645341, 2039645332, 2039645327, 2039645320, 2039645315, 2039645310, 1765376734, 2039645307, 2039645277, 1765376729, 2039645240, 2039645198, 2039645184, 2039645175, 2039645172, 2039645165, 2039645159, 2039645156, 2039645154, 2039645140, 1765376720, 2039645134, 2039645128, 2039645125, 2039645123, 2039645121, 2039645117, 2039645115, 2039645103, 2039645094, 2039645083, 2039645082, 1765376718, 2039645081, 2039645079, 2039645077, 1640686164, 1640686167, 1640686173, 1640686178, 1640686184, 1640686194, 1640686198, 1640686197, 1640546445, 1640546444, 1640546442, 1640546438, 1640546434, 1640546416, 2039645075, 2039645078, 2039645085, 2039645099, 1765376719, 2449289473]}, {"type": "way", "id": 236975503, "nodes": [2449289461, 2449289440, 2449289449, 2449289485, 2449289521, 2449289469, 2449289456, 2449289451, 2449289452, 2449289525, 2449289471, 2449289486, 2449289461]}, {"type": "way", "id": 236975504, "nodes": [2449289496, 2449289443, 2449289484, 2449289517, 2449289501, 2449289510, 2449289455, 2449289522, 2449289495, 2449289515, 2449289531, 2449289529, 2449289511, 2449289500, 2449289496]}, {"type": "way", "id": 236975505, "nodes": [2039645378, 2039645481, 2039645485, 2039645487, 2039645488, 2039645493, 2039645495, 2039645497, 2039645499, 2039645502, 2039645503, 2039645504, 2039645505, 2039645507, 2039645509, 2039645510, 2039645514, 2039645515, 2039645521, 2039645522, 2039645520, 2039645517, 2039645518, 2039645516, 2039645519, 2039645513, 2039645511, 2039645508, 2039645506, 2039645501, 2039645500, 2039645498, 2039645496, 2039645494, 2039645492, 2039645489, 2039645486, 2039645484, 2039645482, 2039645480, 2039645477, 2039645476, 2039645475, 2039645473, 2039645458, 2039645424, 2039645400, 2039645393, 2039645374, 2039645370, 2039645366, 2039645359, 2039645356, 2039645380, 2039645389, 2039645406, 2039645417, 2039645440, 2039645452, 2039645456, 2039645455, 2039645450, 2039645427, 2039645411, 2039645394, 2039645391, 2039645397, 2039645403, 2039645413, 2039645429, 2039645438, 2039645447, 2039645453, 2039645457, 2039645463, 2039645449, 2039645446, 2039645445, 2039645444, 2039645437, 2039645431, 2039645419, 2039645409, 2039645404, 2039645398, 2039645390, 2039645387, 2039645381, 2039645379, 2039645377, 2039645375, 2039645369, 2039645362, 2039645358, 2039645357, 2039645360, 2039645364, 2039645367, 2039645371, 2039645385, 2039645392, 2039645402, 2039645407, 2039645415, 2039645421, 2039645433, 2039645439, 2039645443, 2039645462, 2039645465, 2039645464, 2039645459, 2039645461, 2039645466, 2039645468, 2039645467, 2039645460, 2039645454, 2039645451, 2039645448, 2039645436, 2039645430, 2039645423, 1765376736, 2039645405, 2039645396, 2039645378], "tags": {"name": "South Tail", "natural": "beach", "surface": "sand"}}, {"type": "way", "id": 236975506, "nodes": [2449289506, 2449289530, 2449289467, 2449289445, 2449289457, 2449289475, 2449289506]}, {"type": "way", "id": 236975507, "nodes": [2449289450, 2449289502, 2449289507, 2449289516, 2449289462, 2449289460, 2449289519, 2449289442, 2449289447, 2449289523, 2449289520, 2449289450]}, {"type": "way", "id": 236975508, "nodes": [2449289528, 2449289503, 2449289464, 2449289504, 2449289518, 2449289497, 2449289509, 2449289466, 2449289465, 2449289528]}, {"type": "way", "id": 428800947, "nodes": [1912553490, 567148349, 567148351, 567148338, 567148381, 567148382, 567148387, 567148386, 567148383, 4279001326, 7747833553, 7747833552, 10748990290, 7747822178, 7747822179, 7747822180, 7747822181, 7747822182, 7747833287, 7747833286, 7747833285, 7747822184, 531626450, 7747822183, 1746812736, 531626455, 7747822176, 531626463, 531626466, 531626470, 531626474, 531626479, 531626324, 531626338, 531626347, 531626363, 531626364, 340456253, 542236254, 567148307, 567148306, 567148305, 567148280, 567148281, 4279001324, 4279001327, 7240921173, 7240921172, 567148339, 1912553490], "tags": {"access": "yes", "name": "Croyde Beach", "natural": "beach", "surface": "sand"}}, {"type": "way", "id": 681182284, "nodes": [1978000134, 1978000016, 1561187275, 1978000010, 1978000095, 1978000127, 1978000178, 1978000140]}, {"type": "way", "id": 681182285, "nodes": [2039645353, 224705196, 224705197, 224705200, 1978000134]}, {"type": "way", "id": 1203471818, "nodes": [11155851407, 11155851408, 11155851406, 1801881714, 1801881715, 11155851407], "tags": {"natural": "beach"}}, {"type": "way", "id": 1203547587, "nodes": [1640546338, 11156524125, 11156524124, 11156524123, 11156524137, 11156524135, 11156524134, 11156524147, 11156524138, 11156524139, 1640546276, 1640546282, 1640546293, 1640546296, 11156524140, 1640546311, 1640546325, 1640546338], "tags": {"natural": "beach"}}, {"type": "way", "id": 1203547588, "nodes": [11156524132, 11156524141, 11156524142, 11156524143, 11156524144, 11156524145, 11156524146, 11156524127, 11156524128, 11156524129, 11156524130, 11156524131, 11156524132], "tags": {"natural": "beach"}}, {"type": "way", "id": 1320452395, "nodes": [12219284178, 249630263, 48961713, 320377685, 320377686, 320377687, 3906304050, 320377688, 320377689, 48961723, 320377690, 320377691, 10572995737, 320377493, 3906304661, 12219284048, 12219284049, 320377494, 12219283996, 48961725, 320377496, 12219284004, 320377497, 12219284003, 12219284002, 320377498, 48961727, 320377500, 48961730, 320377501, 320377502, 48961732, 10751276164, 10751276165, 3379299746, 3379299751, 3379299763, 3379299773, 3379299777, 3379299778, 3379299996, 3379300002, 12219284178], "tags": {"foot": "yes", "name": "Putsborough Sands", "natural": "beach", "operator": "Parkin Estates", "sport": "surfing;swimming", "surface": "sand", "vehicle": "no"}}, {"type": "relation", "id": 3188399, "members": [{"type": "way", "ref": 236975508, "role": "inner"}, {"type": "way", "ref": 236975504, "role": "inner"}, {"type": "way", "ref": 236975503, "role": "inner"}, {"type": "way", "ref": 236975506, "role": "inner"}, {"type": "way", "ref": 236975507, "role": "inner"}, {"type": "way", "ref": 236975502, "role": "outer"}], "tags": {"name": "South Gut", "natural": "beach", "surface": "sand", "tidal": "yes", "type": "multipolygon"}}, {"type": "relation", "id": 9452840, "members": [{"type": "way", "ref": 236970693, "role": "outer"}, {"type": "way", "ref": 681182285, "role": "outer"}, {"type": "way", "ref": 681182284, "role": "outer"}], "tags": {"name": "Saunton Sands", "natural": "beach", "surface": "sand", "type": "multipolygon", "wikidata": "Q7427501", "wikipedia": "en:Saunton Sands"}}]}