{"version": 0.6, "generator": "Overpass API 0.7.62.5 1bd436f1", "osm3s": {"timestamp_osm_base": "2025-04-16T18:55:41Z", "copyright": "The data included in this document is from www.openstreetmap.org. The data is made available under ODbL."}, "elements": [{"type": "node", "id": 197304069, "lat": 53.0790091, "lon": -1.7885583, "tags": {"name": "Dove Holes", "natural": "cave_entrance", "note": "small caves"}}, {"type": "node", "id": 671305170, "lat": 53.0917556, "lon": -1.8541538, "tags": {"name": "Thor's Cave", "name:ru": "\u041f\u0435\u0449\u0435\u0440\u0430 \u0422\u043e\u0440\u0430", "natural": "cave_entrance", "tourism": "attraction", "wikidata": "Q4362276", "wikipedia": "en:Thor's Cave"}}, {"type": "node", "id": 765638553, "lat": 53.0717065, "lon": -1.7868447, "tags": {"natural": "cave_entrance", "source": "survey"}}, {"type": "node", "id": 1451255758, "lat": 53.0749682, "lon": -1.7888886, "tags": {"natural": "cave_entrance"}}, {"type": "node", "id": 1451255759, "lat": 53.0750434, "lon": -1.7898557, "tags": {"natural": "cave_entrance"}}, {"type": "node", "id": 1717115806, "lat": 53.1734161, "lon": -1.6783583, "tags": {"natural": "cave_entrance", "source": "View from path"}}, {"type": "node", "id": 1777421444, "lat": 53.1023851, "lon": -1.859211, "tags": {"name": "Nan Tor Cave", "natural": "cave_entrance"}}, {"type": "node", "id": 1986526629, "lat": 53.1898569, "lon": -1.7458946, "tags": {"name": "Lathkill Head Cave", "natural": "cave_entrance"}}, {"type": "node", "id": 2156084479, "lat": 53.1226988, "lon": -1.8052663, "tags": {"natural": "cave_entrance"}}, {"type": "node", "id": 2383400886, "lat": 53.1327212, "lon": -1.5836477, "tags": {"name": "Jug Hole", "natural": "cave_entrance"}}, {"type": "node", "id": 2865146618, "lat": 53.0836283, "lon": -1.8411516, "tags": {"name": "Lynx Cave", "natural": "cave_entrance"}}, {"type": "node", "id": 2866098997, "lat": 53.1234882, "lon": -1.5640998, "tags": {"access": "customers", "direction": "165", "fee": "yes", "name": "Great Rutland Cavern", "natural": "cave_entrance"}}, {"type": "node", "id": 2866126421, "lat": 53.1245549, "lon": -1.5654343, "tags": {"access": "customers", "direction": "75", "fee": "yes", "name": "Great Masson Cavern", "natural": "cave_entrance"}}, {"type": "node", "id": 2866126462, "lat": 53.1258512, "lon": -1.5672662, "tags": {"access": "no", "direction": "110", "name": "Great Masson Cavern", "natural": "cave_entrance"}}, {"type": "node", "id": 3101562377, "lat": 53.1090763, "lon": -1.7871787, "tags": {"natural": "cave_entrance"}}, {"type": "node", "id": 3563464508, "lat": 53.0982265, "lon": -1.853253, "tags": {"name": "Old Hannah's Hole", "natural": "cave_entrance"}}, {"type": "node", "id": 3793279753, "lat": 53.1224815, "lon": -1.8047591, "tags": {"natural": "cave_entrance"}}, {"type": "node", "id": 3878956504, "lat": 53.1919937, "lon": -1.7045263, "tags": {"natural": "cave_entrance", "source": "View from path"}}, {"type": "node", "id": 3917588189, "lat": 53.1137456, "lon": -1.5591274, "tags": {"fee": "no", "natural": "cave_entrance"}}, {"type": "node", "id": 3917588196, "lat": 53.1161395, "lon": -1.5591001, "tags": {"fee": "no", "natural": "cave_entrance"}}, {"type": "node", "id": 4114903384, "lat": 53.1905343, "lon": -1.7542826, "tags": {"natural": "cave_entrance"}}, {"type": "node", "id": 4624328317, "lat": 53.1272179, "lon": -1.5703773, "tags": {"name": "Great Masson Cavern", "natural": "cave_entrance"}}, {"type": "node", "id": 4764996859, "lat": 53.1219442, "lon": -1.5672721, "tags": {"name": "Devonshire Cavern", "natural": "cave_entrance"}}, {"type": "node", "id": 4935973661, "lat": 53.1160231, "lon": -1.5647127, "tags": {"access": "private", "name": "Cumberland Cavern", "natural": "cave_entrance"}}, {"type": "node", "id": 5212657926, "lat": 53.0696363, "lon": -1.7851603, "tags": {"name": "Reynard's Cave", "natural": "cave_entrance"}}, {"type": "node", "id": 6700855691, "lat": 53.1918243, "lon": -1.7085086, "tags": {"natural": "cave_entrance"}}, {"type": "node", "id": 6700855694, "lat": 53.192242, "lon": -1.7079132, "tags": {"natural": "cave_entrance"}}, {"type": "node", "id": 7161245317, "lat": 53.0583265, "lon": -1.7786691, "tags": {"fee": "no", "natural": "cave_entrance"}}, {"type": "node", "id": 7291780011, "lat": 53.0743033, "lon": -1.5943882, "tags": {"access": "private", "alt_name": "Dream Mine", "name": "Dream Cave", "natural": "cave_entrance", "wikidata": "Q79284423", "wikipedia": "en:Dream Cave"}}, {"type": "node", "id": 7688994365, "lat": 53.2045864, "lon": -1.8883509, "tags": {"natural": "cave_entrance"}}, {"type": "node", "id": 7784526433, "lat": 53.1894105, "lon": -1.7105859, "tags": {"natural": "cave_entrance"}}, {"type": "node", "id": 7803744621, "lat": 53.1577095, "lon": -1.6607304, "tags": {"name": "Hermits Cave", "natural": "cave_entrance"}}, {"type": "node", "id": 8862234411, "lat": 53.1282202, "lon": -1.5709872, "tags": {"access": "no", "name": "Gentlewoman's Pipe", "natural": "cave_entrance", "note": "As of November 2018, access to this cave has been blocked by the landowner. Do not attempt access until issue has been resolved by DCA."}}, {"type": "node", "id": 8862259272, "lat": 53.1311613, "lon": -1.559756, "tags": {"access": "permit", "name": "Ringing Rake Sough", "natural": "cave_entrance"}}, {"type": "node", "id": 8862269521, "lat": 53.1338791, "lon": -1.590592, "tags": {"access": "private", "name": "Oxclose", "natural": "cave_entrance"}}, {"type": "node", "id": 10101485455, "lat": 52.9892385, "lon": -1.8597205, "tags": {"natural": "cave_entrance"}}, {"type": "node", "id": 10101667967, "lat": 52.9877776, "lon": -1.859366, "tags": {"natural": "cave_entrance"}}, {"type": "node", "id": 10180672043, "lat": 53.1272062, "lon": -1.5573704, "tags": {"access": "no", "barrier": "gate", "natural": "cave_entrance"}}, {"type": "node", "id": 12459750117, "lat": 53.0415169, "lon": -1.9999539, "tags": {"name": "Prices Cave", "natural": "cave_entrance"}}]}