{"version": 0.6, "generator": "Overpass API 0.7.62.5 1bd436f1", "osm3s": {"timestamp_osm_base": "2025-04-16T20:04:30Z", "copyright": "The data included in this document is from www.openstreetmap.org. The data is made available under ODbL."}, "elements": [{"type": "node", "id": 4073526166, "lat": 58.8551781, "lon": 0.1089836}, {"type": "node", "id": 4073526167, "lat": 58.9239917, "lon": 0.0969412}, {"type": "node", "id": 4073526168, "lat": 59.0618212, "lon": -0.2882703}, {"type": "node", "id": 4073529655, "lat": 58.8190509, "lon": -0.0028386}, {"type": "node", "id": 4073529656, "lat": 58.8303137, "lon": -0.1640534}, {"type": "node", "id": 4073529659, "lat": 58.987463, "lon": -0.139554}, {"type": "node", "id": 4073529660, "lat": 59.1926915, "lon": -0.1008878}, {"type": "node", "id": 4073529661, "lat": 59.2551524, "lon": -0.2079635}, {"type": "node", "id": 4073529662, "lat": 59.3179229, "lon": -0.3773572}, {"type": "node", "id": 4073530092, "lat": 59.093149, "lon": -0.5267451}, {"type": "node", "id": 4073530289, "lat": 58.8271202, "lon": -0.118068}, {"type": "node", "id": 4073530397, "lat": 58.9595312, "lon": -0.4052968}, {"type": "node", "id": 4073530489, "lat": 58.970441, "lon": 0.0745768}, {"type": "way", "id": 405131802, "nodes": [4073526166, 4073529655, 4073530289, 4073529656, 4073530397, 4073530092, 4073529662, 4073529661, 4073529660, 4073526168, 4073529659, 4073530489, 4073526167, 4073526166], "tags": {"leisure": "nature_reserve", "name": "Central Fladen Marine Protected Area", "name:gd": "Sgpire Ghl\u00e8idhte Mhara Fladen Meadhanach", "protect_class": "98", "protection_title": "Marine Protected Area"}}]}